Workbook

Sheet Executive Dashboard
B2: 🛠️ Machine Spare Part Strategic Control Dashboard
B5: MC Group | C5: Risk Zone | D5: Items Count | E5: Inventory Value (THB) | F5: Reorder Items | H5: 📊 สรุปจำนวนชิ้นส่วนแยกตามระดับความสำคัญ (Machine Criticality)
B6: Forming | C6: 🔴 วิกฤต! (ของหมด) | D6: =COUNTIF('Master Data'!$W$2:$W$89, C6) -> 73 | E6: =SUMIF('Master Data'!$W$2:$W$89, C6, 'Master Data'!$U$2:$U$89) -> 0 | F6: =COUNTIFS('Master Data'!$W$2:$W$89,C6,'Master Data'!$V$2:$V$89, "ควรสั่งซื้อ") -> 73 | G6: =COUNTIFS('Master Data'!$B$2:$B$74,B6,'Master Data'!$W$2:$W$89,C6,'Master Data'!$V$2:$V$74, "*ควรสั่งซื้อ*") -> #VALUE! | H6: Criticality Score | I6: จำนวนอะไหล่ (รายการ)
C7: 🟡 ควรสั่งซื้อ (ต่ำกว่า ROP) | D7: =COUNTIF('Master Data'!$W$2:$W$89, C7) -> 9 | E7: =SUMIF('Master Data'!$W$2:$W$89, C7, 'Master Data'!$U$2:$U$89) -> 9000 | F7: =COUNTIFS('Master Data'!$W$2:$W$89,C7,'Master Data'!$V$2:$V$89, "ควรสั่งซื้อ") -> 9 | G7: =SUM(COUNTIFS('Master Data'!$B$2:$B$74, "Forming", 'Master Data'!$V$2:$V$74, "*วิกฤต*"), COUNTIFS('Master Data'!$B$2:$B$74, "Forming", 'Master Data'!$V$2:$V$74, "*ควรสั่งซื้อ*")) -> 40 | H7: 9 | I7: =COUNTIF('Master Data'!X2:X89, 9) -> 39
C8: 🟢 ปกติ | D8: =COUNTIF('Master Data'!$W$2:$W$89, C8) -> 6 | E8: =SUMIF('Master Data'!$W$2:$W$89, C8, 'Master Data'!$U$2:$U$89) -> 0 | F8: =COUNTIFS('Master Data'!$W$2:$W$89,C8,'Master Data'!$V$2:$V$89, "ควรสั่งซื้อ") -> 0 | H8: 6 | I8: =COUNTIF('Master Data'!X2:X89, 6) -> 47
C9: Total | D9: =SUM(D6:D8) -> 88 | E9: =SUM(E6:E8) -> 9000 | F9: =SUM(F6:F8) -> 82 | H9: 3 | I9: =COUNTIF('Master Data'!X2:X89, 3) -> 2
C23: ⚠️ รายการแจ้งเตือนชิ้นส่วนวิกฤตต่ำกว่า ROP และจุดสั่งซื้อที่ต้องดำเนินการทันที
C24: Part Code | D24: Part Name | E24: MC Group | F24: Min Stock | G24: ROP | H24: Current Stock | I24: Status Alert | J24: Criticality Score
C25: ='Master Data'!H2 -> PT-01 | D25: ='Master Data'!I2 -> Hydraulic pump | E25: ='Master Data'!B2 -> Forming | F25: ='Master Data'!Q2 -> 1 | G25: ='Master Data'!S2 -> 2 | H25: ='Master Data'!T2 -> 0 | I25: ='Master Data'!W2 -> 🔴 วิกฤต! (ของหมด) | J25: ='Master Data'!X2 -> 6
C26: ='Master Data'!H3 -> PT-02 | D26: ='Master Data'!I3 -> Filter | E26: ='Master Data'!B3 -> Forming | F26: ='Master Data'!Q3 -> 1 | G26: ='Master Data'!S3 -> 2 | H26: ='Master Data'!T3 -> 0 | I26: ='Master Data'!W3 -> 🔴 วิกฤต! (ของหมด) | J26: ='Master Data'!X3 -> 6
C27: ='Master Data'!H4 -> PT-03 | D27: ='Master Data'!I4 -> Oil Mirror | E27: ='Master Data'!B4 -> Forming | F27: ='Master Data'!Q4 -> 1 | G27: ='Master Data'!S4 -> 2 | H27: ='Master Data'!T4 -> 0 | I27: ='Master Data'!W4 -> 🔴 วิกฤต! (ของหมด) | J27: ='Master Data'!X4 -> 6
C28: ='Master Data'!H5 -> PT-04 | D28: ='Master Data'!I5 -> Solenoid Valve releasing cylinder upper | E28: ='Master Data'!B5 -> Forming | F28: ='Master Data'!Q5 -> 1 | G28: ='Master Data'!S5 -> 2 | H28: ='Master Data'!T5 -> 0 | I28: ='Master Data'!W5 -> 🔴 วิกฤต! (ของหมด) | J28: ='Master Data'!X5 -> 6
C29: ='Master Data'!H6 -> PT-05 | D29: ='Master Data'!I6 -> Solenoid Valve Main Cylinder | E29: ='Master Data'!B6 -> Forming | F29: ='Master Data'!Q6 -> 1 | G29: ='Master Data'!S6 -> 2 | H29: ='Master Data'!T6 -> 1 | I29: ='Master Data'!W6 -> 🟡 ควรสั่งซื้อ (ต่ำกว่า ROP) | J29: ='Master Data'!X6 -> 6
C30: ='Master Data'!H7 -> PT-06 | D30: ='Master Data'!I7 -> Solenoid Valve Mold Move in Cylinder | E30: ='Master Data'!B7 -> Forming | F30: ='Master Data'!Q7 -> 1 | G30: ='Master Data'!S7 -> 2 | H30: ='Master Data'!T7 -> 1 | I30: ='Master Data'!W7 -> 🟡 ควรสั่งซื้อ (ต่ำกว่า ROP) | J30: ='Master Data'!X7 -> 6
C31: ='Master Data'!H8 -> PT-07 | D31: ='Master Data'!I8 -> Counterbalance Valve | E31: ='Master Data'!B8 -> Forming | F31: ='Master Data'!Q8 -> 1 | G31: ='Master Data'!S8 -> 2 | H31: ='Master Data'!T8 -> 0 | I31: ='Master Data'!W8 -> 🔴 วิกฤต! (ของหมด) | J31: ='Master Data'!X8 -> 6
C32: ='Master Data'!H9 -> PT-08 | D32: ='Master Data'!I9 -> Counterbalance Valve | E32: ='Master Data'!B9 -> Forming | F32: ='Master Data'!Q9 -> 1 | G32: ='Master Data'!S9 -> 2 | H32: ='Master Data'!T9 -> 0 | I32: ='Master Data'!W9 -> 🔴 วิกฤต! (ของหมด) | J32: ='Master Data'!X9 -> 6
C33: ='Master Data'!H10 -> PT-09 | D33: ='Master Data'!I10 -> Proportion Pressure & Flow Compound Valve | E33: ='Master Data'!B10 -> Forming | F33: ='Master Data'!Q10 -> 1 | G33: ='Master Data'!S10 -> 2 | H33: ='Master Data'!T10 -> 0 | I33: ='Master Data'!W10 -> 🔴 วิกฤต! (ของหมด) | J33: ='Master Data'!X10 -> 6
C34: ='Master Data'!H11 -> PT-10 | D34: ='Master Data'!I11 -> Stop Valve | E34: ='Master Data'!B11 -> Forming | F34: ='Master Data'!Q11 -> 0 | G34: ='Master Data'!S11 -> 0 | H34: ='Master Data'!T11 -> 0 | I34: ='Master Data'!W11 -> 🔴 วิกฤต! (ของหมด) | J34: ='Master Data'!X11 -> 6
C35: ='Master Data'!H12 -> PT-11 | D35: ='Master Data'!I12 -> Wiper Seal | E35: ='Master Data'!B12 -> Forming | F35: ='Master Data'!Q12 -> 0 | G35: ='Master Data'!S12 -> 0 | H35: ='Master Data'!T12 -> 0 | I35: ='Master Data'!W12 -> 🔴 วิกฤต! (ของหมด) | J35: ='Master Data'!X12 -> 6
C36: ='Master Data'!H13 -> PT-12 | D36: ='Master Data'!I13 -> Spindel Seal | E36: ='Master Data'!B13 -> Forming | F36: ='Master Data'!Q13 -> 0 | G36: ='Master Data'!S13 -> 0 | H36: ='Master Data'!T13 -> 0 | I36: ='Master Data'!W13 -> 🔴 วิกฤต! (ของหมด) | J36: ='Master Data'!X13 -> 6
... C38: ='Master Data'!H15 -> PT-14 | D38: ='Master Data'!I15 -> O-Ring | E38: ='Master Data'!B15 -> Forming | F38: ='Master Data'!Q15 -> 0 | G38: ='Master Data'!S15 -> 0 | H38: ='Master Data'!T15 -> 0 | I38: ='Master Data'!W15 -> 🔴 วิกฤต! (ของหมด) | J38: ='Master Data'!X15 -> 3

Sheet Master Data
A1: Item | B1: MC Group | C1: MC Type | D1: MC Code | E1: Machine Name | F1: MC Common | G1: Location Use | H1: Part Code | I1: Part Name | J1: Machine Rank | K1: Brand/Maker | L1: Part Rank | M1: Unit | N1: Price Unit (Baht) | O1: Keeping Area | P1: Max Stock | Q1: Min Stock | R1: Safety Stock (Formula) | S1: ROP (Reorder Point) | T1: Current Stock | U1: Amount (Baht) | V1: Status Alert | W1: Risk Zone | X1: Machine Criticality Score | Y1: Owner (Responsibility) | Z1: Lead Time (Days) | AA1: Location Order | AB1: Remark
A2: 1 | B2: Forming | C2: Vacuum | D2: C16 | E2: 200 Ton | F2: All | G2: Main Hyd. | H2: PT-01 | I2: Hydraulic pump | J2: B | K2: TECO | L2: Medium | M2: PCS | N2: 0 | O2: AR-01 | P2: 2 | Q2: 1 | R2: =ROUND(Q2*0.5,0) -> 1 | S2: =Q2+R2 -> 2 | T2: =SUMIF('Stock In Log'!C:C, H2, 'Stock In Log'!D:D) - SUMIF('Stock Out Log'!C:C, H2, 'Stock Out Log'!D:D) -> 0 | U2: =N2*T2 -> 0 | V2: =IF(T2<=0,"ควรสั่งซื้อ", IF(T2<=S2,"ควรสั่งซื้อ","ปกติ")) -> ควรสั่งซื้อ | W2: =IF(T2<=0, "🔴 วิกฤต! (ของหมด)", IF(T2<=S2, "🟡 ควรสั่งซื้อ (ต่ำกว่า ROP)", "🟢 ปกติ")) -> 🔴 วิกฤต! (ของหมด) | X2: 6 | Y2: Maintenance Team | Z2: 0
A3: 2 | B3: Forming | C3: Vacuum | D3: B17 | E3: 200 Ton | F3: B14,B15,B16,B18,B19 | G3: Main Hyd. | H3: PT-02 | I3: Filter | J3: B | L3: Medium | M3: PCS | N3: 0 | O3: AR-02 | P3: 2 | Q3: 1 | R3: =ROUND(Q3*0.5,0) -> 1 | S3: =Q3+R3 -> 2 | T3: =SUMIF('Stock In Log'!C:C, H3, 'Stock In Log'!D:D) - SUMIF('Stock Out Log'!C:C, H3, 'Stock Out Log'!D:D) -> 0 | U3: =N3*T3 -> 0 | V3: =IF(T3<=0,"ควรสั่งซื้อ", IF(T3<=S3,"ควรสั่งซื้อ","ปกติ")) -> ควรสั่งซื้อ | W3: =IF(T3<=0, "🔴 วิกฤต! (ของหมด)", IF(T3<=S3, "🟡 ควรสั่งซื้อ (ต่ำกว่า ROP)", "🟢 ปกติ")) -> 🔴 วิกฤต! (ของหมด) | X3: 6 | Y3: Maintenance Team | Z3: 0
A4: 3 | B4: Forming | C4: Vacuum | D4: B17 | E4: 200 Ton | F4: B18,B19 | G4: Main Hyd. | H4: PT-03 | I4: Oil Mirror | J4: B | L4: Medium | M4: PCS | N4: 0 | O4: AR-03 | P4: 2 | Q4: 1 | R4: =ROUND(Q4*0.5,0) -> 1 | S4: =Q4+R4 -> 2 | T4: =SUMIF('Stock In Log'!C:C, H4, 'Stock In Log'!D:D) - SUMIF('Stock Out Log'!C:C, H4, 'Stock Out Log'!D:D) -> 0 | U4: =N4*T4 -> 0 | V4: =IF(T4<=0,"ควรสั่งซื้อ", IF(T4<=S4,"ควรสั่งซื้อ","ปกติ")) -> ควรสั่งซื้อ | W4: =IF(T4<=0, "🔴 วิกฤต! (ของหมด)", IF(T4<=S4, "🟡 ควรสั่งซื้อ (ต่ำกว่า ROP)", "🟢 ปกติ")) -> 🔴 วิกฤต! (ของหมด) | X4: 6 | Y4: Maintenance Team | Z4: 0
A5: 4 | B5: Forming | C5: Vacuum | D5: - | G5: Main Hyd. | H5: PT-04 | I5: Solenoid Valve releasing cylinder upper | J5: B | K5: Yuken | L5: Medium | M5: PCS | N5: 0 | O5: AR-04 | P5: 2 | Q5: 1 | R5: =ROUND(Q5*0.5,0) -> 1 | S5: =Q5+R5 -> 2 | T5: =SUMIF('Stock In Log'!C:C, H5, 'Stock In Log'!D:D) - SUMIF('Stock Out Log'!C:C, H5, 'Stock Out Log'!D:D) -> 0 | U5: =N5*T5 -> 0 | V5: =IF(T5<=0,"ควรสั่งซื้อ", IF(T5<=S5,"ควรสั่งซื้อ","ปกติ")) -> ควรสั่งซื้อ | W5: =IF(T5<=0, "🔴 วิกฤต! (ของหมด)", IF(T5<=S5, "🟡 ควรสั่งซื้อ (ต่ำกว่า ROP)", "🟢 ปกติ")) -> 🔴 วิกฤต! (ของหมด) | X5: 6 | Y5: Maintenance Team | Z5: 7 | AA5: Local | AB5: Local
A6: 5 | B6: Forming | C6: Vacuum | D6: - | G6: Main Hyd. | H6: PT-05 | I6: Solenoid Valve Main Cylinder | J6: B | K6: Yuken | L6: Medium | M6: PCS | N6: 0 | O6: AR-05 | P6: 2 | Q6: 1 | R6: =ROUND(Q6*0.5,0) -> 1 | S6: =Q6+R6 -> 2 | T6: =SUMIF('Stock In Log'!C:C, H6, 'Stock In Log'!D:D) - SUMIF('Stock Out Log'!C:C, H6, 'Stock Out Log'!D:D) -> 1 | U6: =N6*T6 -> 0 | V6: =IF(T6<=0,"ควรสั่งซื้อ", IF(T6<=S6,"ควรสั่งซื้อ","ปกติ")) -> ควรสั่งซื้อ | W6: =IF(T6<=0, "🔴 วิกฤต! (ของหมด)", IF(T6<=S6, "🟡 ควรสั่งซื้อ (ต่ำกว่า ROP)", "🟢 ปกติ")) -> 🟡 ควรสั่งซื้อ (ต่ำกว่า ROP) | X6: 6 | Y6: Maintenance Team | Z6: 7 | AA6: Local | AB6: Local
A7: 6 | B7: Forming | C7: Vacuum | D7: - | G7: Main Hyd. | H7: PT-06 | I7: Solenoid Valve Mold Move in Cylinder | J7: B | K7: Yuken | L7: Medium | M7: PCS | N7: 0 | O7: AR-06 | P7: 2 | Q7: 1 | R7: =ROUND(Q7*0.5,0) -> 1 | S7: =Q7+R7 -> 2 | T7: =SUMIF('Stock In Log'!C:C, H7, 'Stock In Log'!D:D) - SUMIF('Stock Out Log'!C:C, H7, 'Stock Out Log'!D:D) -> 1 | U7: =N7*T7 -> 0 | V7: =IF(T7<=0,"ควรสั่งซื้อ", IF(T7<=S7,"ควรสั่งซื้อ","ปกติ")) -> ควรสั่งซื้อ | W7: =IF(T7<=0, "🔴 วิกฤต! (ของหมด)", IF(T7<=S7, "🟡 ควรสั่งซื้อ (ต่ำกว่า ROP)", "🟢 ปกติ")) -> 🟡 ควรสั่งซื้อ (ต่ำกว่า ROP) | X7: 6 | Y7: Maintenance Team | Z7: 7 | AA7: Local | AB7: Local
A8: 7 | B8: Forming | C8: Vacuum | D8: - | G8: Main Hyd. | H8: PT-07 | I8: Counterbalance Valve | J8: B | K8: Yuken | L8: Critical | M8: PCS | N8: 0 | O8: AR-07 | P8: 2 | Q8: 1 | R8: =ROUND(Q8*0.5,0) -> 1 | S8: =Q8+R8 -> 2 | T8: =SUMIF('Stock In Log'!C:C, H8, 'Stock In Log'!D:D) - SUMIF('Stock Out Log'!C:C, H8, 'Stock Out Log'!D:D) -> 0 | U8: =N8*T8 -> 0 | V8: =IF(T8<=0,"ควรสั่งซื้อ", IF(T8<=S8,"ควรสั่งซื้อ","ปกติ")) -> ควรสั่งซื้อ | W8: =IF(T8<=0, "🔴 วิกฤต! (ของหมด)", IF(T8<=S8, "🟡 ควรสั่งซื้อ (ต่ำกว่า ROP)", "🟢 ปกติ")) -> 🔴 วิกฤต! (ของหมด) | X8: 6 | Y8: Maintenance Team | Z8: 7 | AA8: Local | AB8: Local
A9: 8 | B9: Forming | C9: Vacuum | D9: - | G9: Main Hyd. | H9: PT-08 | I9: Counterbalance Valve | J9: B | K9: Yuken | L9: Critical | M9: PCS | N9: 0 | O9: AR-08 | P9: 2 | Q9: 1 | R9: =ROUND(Q9*0.5,0) -> 1 | S9: =Q9+R9 -> 2 | T9: =SUMIF('Stock In Log'!C:C, H9, 'Stock In Log'!D:D) - SUMIF('Stock Out Log'!C:C, H9, 'Stock Out Log'!D:D) -> 0 | U9: =N9*T9 -> 0 | V9: =IF(T9<=0,"ควรสั่งซื้อ", IF(T9<=S9,"ควรสั่งซื้อ","ปกติ")) -> ควรสั่งซื้อ | W9: =IF(T9<=0, "🔴 วิกฤต! (ของหมด)", IF(T9<=S9, "🟡 ควรสั่งซื้อ (ต่ำกว่า ROP)", "🟢 ปกติ")) -> 🔴 วิกฤต! (ของหมด) | X9: 6 | Y9: Maintenance Team | Z9: 7 | AA9: Local | AB9: Local
A10: 9 | B10: Forming | C10: Vacuum | D10: - | G10: Main Hyd. | H10: PT-09 | I10: Proportion Pressure & Flow Compound Valve | J10: B | K10: Yuken | L10: Low | M10: PCS | N10: 31000 | O10: AR-09 | P10: 2 | Q10: 1 | R10: =ROUND(Q10*0.5,0) -> 1 | S10: =Q10+R10 -> 2 | T10: =SUMIF('Stock In Log'!C:C, H10, 'Stock In Log'!D:D) - SUMIF('Stock Out Log'!C:C, H10, 'Stock Out Log'!D:D) -> 0 | U10: =N10*T10 -> 0 | V10: =IF(T10<=0,"ควรสั่งซื้อ", IF(T10<=S10,"ควรสั่งซื้อ","ปกติ")) -> ควรสั่งซื้อ | W10: =IF(T10<=0, "🔴 วิกฤต! (ของหมด)", IF(T10<=S10, "🟡 ควรสั่งซื้อ (ต่ำกว่า ROP)", "🟢 ปกติ")) -> 🔴 วิกฤต! (ของหมด) | X10: 6 | Y10: Maintenance Team | Z10: 7 | AA10: Local | AB10: Local
A11: 10 | B11: Forming | C11: Vacuum | D11: - | G11: Main Hyd. | H11: PT-10 | I11: Stop Valve | J11: B | K11: Yuken | L11: Low | M11: PCS | N11: 0 | O11: AR-10 | P11: 0 | Q11: 0 | R11: =ROUND(Q11*0.5,0) -> 0 | S11: =Q11+R11 -> 0 | T11: =SUMIF('Stock In Log'!C:C, H11, 'Stock In Log'!D:D) - SUMIF('Stock Out Log'!C:C, H11, 'Stock Out Log'!D:D) -> 0 | U11: =N11*T11 -> 0 | V11: =IF(T11<=0,"ควรสั่งซื้อ", IF(T11<=S11,"ควรสั่งซื้อ","ปกติ")) -> ควรสั่งซื้อ | W11: =IF(T11<=0, "🔴 วิกฤต! (ของหมด)", IF(T11<=S11, "🟡 ควรสั่งซื้อ (ต่ำกว่า ROP)", "🟢 ปกติ")) -> 🔴 วิกฤต! (ของหมด) | X11: 6 | Y11: Maintenance Team | Z11: 0
A12: 11 | B12: Forming | C12: Vacuum | D12: - | G12: Cylinder Hyd | H12: PT-11 | I12: Wiper Seal | J12: B | M12: PCS | N12: 0 | O12: AR-11 | P12: 0 | Q12: 0 | R12: =ROUND(Q12*0.5,0) -> 0 | S12: =Q12+R12 -> 0 | T12: =SUMIF('Stock In Log'!C:C, H12, 'Stock In Log'!D:D) - SUMIF('Stock Out Log'!C:C, H12, 'Stock Out Log'!D:D) -> 0 | U12: =N12*T12 -> 0 | V12: =IF(T12<=0,"ควรสั่งซื้อ", IF(T12<=S12,"ควรสั่งซื้อ","ปกติ")) -> ควรสั่งซื้อ | W12: =IF(T12<=0, "🔴 วิกฤต! (ของหมด)", IF(T12<=S12, "🟡 ควรสั่งซื้อ (ต่ำกว่า ROP)", "🟢 ปกติ")) -> 🔴 วิกฤต! (ของหมด) | X12: 6 | Y12: Maintenance Team | Z12: 0
A13: 12 | B13: Forming | C13: Vacuum | D13: - | G13: Cylinder Hyd | H13: PT-12 | I13: Spindel Seal | J13: B | M13: PCS | N13: 0 | O13: AR-12 | P13: 0 | Q13: 0 | R13: =ROUND(Q13*0.5,0) -> 0 | S13: =Q13+R13 -> 0 | T13: =SUMIF('Stock In Log'!C:C, H13, 'Stock In Log'!D:D) - SUMIF('Stock Out Log'!C:C, H13, 'Stock Out Log'!D:D) -> 0 | U13: =N13*T13 -> 0 | V13: =IF(T13<=0,"ควรสั่งซื้อ", IF(T13<=S13,"ควรสั่งซื้อ","ปกติ")) -> ควรสั่งซื้อ | W13: =IF(T13<=0, "🔴 วิกฤต! (ของหมด)", IF(T13<=S13, "🟡 ควรสั่งซื้อ (ต่ำกว่า ROP)", "🟢 ปกติ")) -> 🔴 วิกฤต! (ของหมด) | X13: 6 | Y13: Maintenance Team | Z13: 0
A14: 13 | B14: Forming | C14: Vacuum | D14: - | G14: Cylinder Hyd | H14: PT-13 | I14: O-Ring | J14: B | M14: PCS | N14: 0 | O14: AR-13 | P14: 0 | Q14: 0 | R14: =ROUND(Q14*0.5,0) -> 0 | S14: =Q14+R14 -> 0 | T14: =SUMIF('Stock In Log'!C:C, H14, 'Stock In Log'!D:D) - SUMIF('Stock Out Log'!C:C, H14, 'Stock Out Log'!D:D) -> 0 | U14: =N14*T14 -> 0 | V14: =IF(T14<=0,"ควรสั่งซื้อ", IF(T14<=S14,"ควรสั่งซื้อ","ปกติ")) -> ควรสั่งซื้อ | W14: =IF(T14<=0, "🔴 วิกฤต! (ของหมด)", IF(T14<=S14, "🟡 ควรสั่งซื้อ (ต่ำกว่า ROP)", "🟢 ปกติ")) -> 🔴 วิกฤต! (ของหมด) | X14: 6 | Y14: Maintenance Team | Z14: 0
A15: 14 | B15: Forming | C15: Vacuum | D15: - | G15: Cylinder Hyd | H15: PT-14 | I15: O-Ring | N15: 0 | O15: AR-14 | P15: 0 | Q15: 0 | R15: =ROUND(Q15*0.5,0) -> 0 | S15: =Q15+R15 -> 0 | T15: =SUMIF('Stock In Log'!C:C, H15, 'Stock In Log'!D:D) - SUMIF('Stock Out Log'!C:C, H15, 'Stock Out Log'!D:D) -> 0 | U15: =N15*T15 -> 0 | V15: =IF(T15<=0,"ควรสั่งซื้อ", IF(T15<=S15,"ควรสั่งซื้อ","ปกติ")) -> ควรสั่งซื้อ | W15: =IF(T15<=0, "🔴 วิกฤต! (ของหมด)", IF(T15<=S15, "🟡 ควรสั่งซื้อ (ต่ำกว่า ROP)", "🟢 ปกติ")) -> 🔴 วิกฤต! (ของหมด) | X15: 3 | Y15: Store Keeper | Z15: 0
A16: 15 | B16: Forming | C16: Vacuum | D16: - | G16: Vacuum Unit | H16: PT-15 | I16: Vacuum pump Motor | J16: B | M16: PCS | N16: 0 | O16: AR-15 | P16: 0 | Q16: 0 | R16: =ROUND(Q16*0.5,0) -> 0 | S16: =Q16+R16 -> 0 | T16: =SUMIF('Stock In Log'!C:C, H16, 'Stock In Log'!D:D) - SUMIF('Stock Out Log'!C:C, H16, 'Stock Out Log'!D:D) -> 0 | U16: =N16*T16 -> 0 | V16: =IF(T16<=0,"ควรสั่งซื้อ", IF(T16<=S16,"ควรสั่งซื้อ","ปกติ")) -> ควรสั่งซื้อ | W16: =IF(T16<=0, "🔴 วิกฤต! (ของหมด)", IF(T16<=S16, "🟡 ควรสั่งซื้อ (ต่ำกว่า ROP)", "🟢 ปกติ")) -> 🔴 วิกฤต! (ของหมด) | X16: 6 | Y16: Maintenance Team | Z16: 0
A17: 16 | B17: Forming | C17: Vacuum | D17: - | G17: Vacuum Unit | H17: PT-16 | I17: Solenoid Valve | J17: B | K17: Mindman | M17: PCS | N17: 0 | O17: AR-16 | P17: 0 | Q17: 0 | R17: =ROUND(Q17*0.5,0) -> 0 | S17: =Q17+R17 -> 0 | T17: =SUMIF('Stock In Log'!C:C, H17, 'Stock In Log'!D:D) - SUMIF('Stock Out Log'!C:C, H17, 'Stock Out Log'!D:D) -> 0 | U17: =N17*T17 -> 0 | V17: =IF(T17<=0,"ควรสั่งซื้อ", IF(T17<=S17,"ควรสั่งซื้อ","ปกติ")) -> ควรสั่งซื้อ | W17: =IF(T17<=0, "🔴 วิกฤต! (ของหมด)", IF(T17<=S17, "🟡 ควรสั่งซื้อ (ต่ำกว่า ROP)", "🟢 ปกติ")) -> 🔴 วิกฤต! (ของหมด) | X17: 6 | Y17: Maintenance Team | Z17: 0
A18: 17 | B18: Forming | C18: Vacuum | D18: - | G18: Vacuum Unit | H18: PT-17 | I18: Air Switch | J18: B | M18: PCS | N18: 0 | O18: AR-17 | P18: 0 | Q18: 0 | R18: =ROUND(Q18*0.5,0) -> 0 | S18: =Q18+R18 -> 0 | T18: =SUMIF('Stock In Log'!C:C, H18, 'Stock In Log'!D:D) - SUMIF('Stock Out Log'!C:C, H18, 'Stock Out Log'!D:D) -> 0 | U18: =N18*T18 -> 0 | V18: =IF(T18<=0,"ควรสั่งซื้อ", IF(T18<=S18,"ควรสั่งซื้อ","ปกติ")) -> ควรสั่งซื้อ | W18: =IF(T18<=0, "🔴 วิกฤต! (ของหมด)", IF(T18<=S18, "🟡 ควรสั่งซื้อ (ต่ำกว่า ROP)", "🟢 ปกติ")) -> 🔴 วิกฤต! (ของหมด) | X18: 6 | Y18: Maintenance Team | Z18: 0
A19: 18 | B19: Forming | C19: Vacuum | D19: - | G19: Vacuum Unit | H19: PT-18 | I19: Pressure Switch | J19: B | M19: PCS | N19: 0 | O19: AR-18 | P19: 0 | Q19: 0 | R19: =ROUND(Q19*0.5,0) -> 0 | S19: =Q19+R19 -> 0 | T19: =SUMIF('Stock In Log'!C:C, H19, 'Stock In Log'!D:D) - SUMIF('Stock Out Log'!C:C, H19, 'Stock Out Log'!D:D) -> 0 | U19: =N19*T19 -> 0 | V19: =IF(T19<=0,"ควรสั่งซื้อ", IF(T19<=S19,"ควรสั่งซื้อ","ปกติ")) -> ควรสั่งซื้อ | W19: =IF(T19<=0, "🔴 วิกฤต! (ของหมด)", IF(T19<=S19, "🟡 ควรสั่งซื้อ (ต่ำกว่า ROP)", "🟢 ปกติ")) -> 🔴 วิกฤต! (ของหมด) | X19: 6 | Y19: Maintenance Team | Z19: 0
A20: 19 | B20: Forming | C20: Vacuum | D20: - | G20: Electrical System | H20: PT-19 | I20: Breaker Main | J20: B | K20: Fuji | M20: PCS | N20: 0 | O20: AR-19 | P20: 0 | Q20: 0 | R20: =ROUND(Q20*0.5,0) -> 0 | S20: =Q20+R20 -> 0 | T20: =SUMIF('Stock In Log'!C:C, H20, 'Stock In Log'!D:D) - SUMIF('Stock Out Log'!C:C, H20, 'Stock Out Log'!D:D) -> 0 | U20: =N20*T20 -> 0 | V20: =IF(T20<=0,"ควรสั่งซื้อ", IF(T20<=S20,"ควรสั่งซื้อ","ปกติ")) -> ควรสั่งซื้อ | W20: =IF(T20<=0, "🔴 วิกฤต! (ของหมด)", IF(T20<=S20, "🟡 ควรสั่งซื้อ (ต่ำกว่า ROP)", "🟢 ปกติ")) -> 🔴 วิกฤต! (ของหมด) | X20: 6 | Y20: Maintenance Team | Z20: 0
A21: 20 | B21: Forming | C21: Vacuum | D21: - | G21: Electrical System | H21: PT-20 | I21: Breaker Heater | J21: B | K21: Fuji | M21: PCS | N21: 0 | O21: AR-20 | P21: 0 | Q21: 0 | R21: =ROUND(Q21*0.5,0) -> 0 | S21: =Q21+R21 -> 0 | T21: =SUMIF('Stock In Log'!C:C, H21, 'Stock In Log'!D:D) - SUMIF('Stock Out Log'!C:C, H21, 'Stock Out Log'!D:D) -> 0 | U21: =N21*T21 -> 0 | V21: =IF(T21<=0,"ควรสั่งซื้อ", IF(T21<=S21,"ควรสั่งซื้อ","ปกติ")) -> ควรสั่งซื้อ | W21: =IF(T21<=0, "🔴 วิกฤต! (ของหมด)", IF(T21<=S21, "🟡 ควรสั่งซื้อ (ต่ำกว่า ROP)", "🟢 ปกติ")) -> 🔴 วิกฤต! (ของหมด) | X21: 6 | Y21: Maintenance Team | Z21: 0
A22: 21 | B22: Forming | C22: Vacuum | D22: - | G22: Electrical System | H22: PT-21 | I22: Power Supply | J22: B | K22: Omron | M22: PCS | N22: 0 | O22: AR-21 | P22: 0 | Q22: 0 | R22: =ROUND(Q22*0.5,0) -> 0 | S22: =Q22+R22 -> 0 | T22: =SUMIF('Stock In Log'!C:C, H22, 'Stock In Log'!D:D) - SUMIF('Stock Out Log'!C:C, H22, 'Stock Out Log'!D:D) -> 0 | U22: =N22*T22 -> 0 | V22: =IF(T22<=0,"ควรสั่งซื้อ", IF(T22<=S22,"ควรสั่งซื้อ","ปกติ")) -> ควรสั่งซื้อ | W22: =IF(T22<=0, "🔴 วิกฤต! (ของหมด)", IF(T22<=S22, "🟡 ควรสั่งซื้อ (ต่ำกว่า ROP)", "🟢 ปกติ")) -> 🔴 วิกฤต! (ของหมด) | X22: 6 | Y22: Maintenance Team | Z22: 0
A23: 22 | B23: Forming | C23: Vacuum | D23: - | G23: Electrical System | H23: PT-22 | I23: Temperature Controller | J23: B | K23: Omron | M23: PCS | N23: 0 | O23: AR-22 | P23: 5 | Q23: 3 | R23: =ROUND(Q23*0.5,0) -> 2 | S23: =Q23+R23 -> 5 | T23: =SUMIF('Stock In Log'!C:C, H23, 'Stock In Log'!D:D) - SUMIF('Stock Out Log'!C:C, H23, 'Stock Out Log'!D:D) -> 7 | U23: =N23*T23 -> 0 | V23: =IF(T23<=0,"ควรสั่งซื้อ", IF(T23<=S23,"ควรสั่งซื้อ","ปกติ")) -> ปกติ | W23: =IF(T23<=0, "🔴 วิกฤต! (ของหมด)", IF(T23<=S23, "🟡 ควรสั่งซื้อ (ต่ำกว่า ROP)", "🟢 ปกติ")) -> 🟢 ปกติ | X23: 6 | Y23: Maintenance Team | Z23: 0 | AA23: oversee
A24: 23 | B24: Forming | C24: Vacuum | D24: - | G24: Electrical System | H24: PT-23 | I24: Magnetic Contactor Motor pump | J24: B | K24: Fuji | M24: PCS | N24: 0 | O24: AR-23 | P24: 0 | Q24: 0 | R24: =ROUND(Q24*0.5,0) -> 0 | S24: =Q24+R24 -> 0 | T24: =SUMIF('Stock In Log'!C:C, H24, 'Stock In Log'!D:D) - SUMIF('Stock Out Log'!C:C, H24, 'Stock Out Log'!D:D) -> 2 | U24: =N24*T24 -> 0 | V24: =IF(T24<=0,"ควรสั่งซื้อ", IF(T24<=S24,"ควรสั่งซื้อ","ปกติ")) -> ปกติ | W24: =IF(T24<=0, "🔴 วิกฤต! (ของหมด)", IF(T24<=S24, "🟡 ควรสั่งซื้อ (ต่ำกว่า ROP)", "🟢 ปกติ")) -> 🟢 ปกติ | X24: 6 | Y24: Maintenance Team | Z24: 0 | AA24: oversee
A25: 24 | B25: Forming | C25: Vacuum | D25: - | G25: Electrical System | H25: PT-24 | I25: Magnetic Switch Heater | J25: B | K25: Fuji | M25: PCS | N25: 0 | O25: AR-24 | P25: 0 | Q25: 0 | R25: =ROUND(Q25*0.5,0) -> 0 | S25: =Q25+R25 -> 0 | T25: =SUMIF('Stock In Log'!C:C, H25, 'Stock In Log'!D:D) - SUMIF('Stock Out Log'!C:C, H25, 'Stock Out Log'!D:D) -> 2 | U25: =N25*T25 -> 0 | V25: =IF(T25<=0,"ควรสั่งซื้อ", IF(T25<=S25,"ควรสั่งซื้อ","ปกติ")) -> ปกติ | W25: =IF(T25<=0, "🔴 วิกฤต! (ของหมด)", IF(T25<=S25, "🟡 ควรสั่งซื้อ (ต่ำกว่า ROP)", "🟢 ปกติ")) -> 🟢 ปกติ | X25: 6 | Y25: Maintenance Team | Z25: 0 | AA25: oversee
A26: 25 | B26: Forming | C26: Vacuum | D26: - | F26: All | G26: Electrical System | H26: PT-25 | I26: Overload Motor pump Hyd | J26: B | K26: Fuji | M26: PCS | N26: 0 | O26: AR-25 | P26: 5 | Q26: 3 | R26: =ROUND(Q26*0.5,0) -> 2 | S26: =Q26+R26 -> 5 | T26: =SUMIF('Stock In Log'!C:C, H26, 'Stock In Log'!D:D) - SUMIF('Stock Out Log'!C:C, H26, 'Stock Out Log'!D:D) -> 6 | U26: =N26*T26 -> 0 | V26: =IF(T26<=0,"ควรสั่งซื้อ", IF(T26<=S26,"ควรสั่งซื้อ","ปกติ")) -> ปกติ | W26: =IF(T26<=0, "🔴 วิกฤต! (ของหมด)", IF(T26<=S26, "🟡 ควรสั่งซื้อ (ต่ำกว่า ROP)", "🟢 ปกติ")) -> 🟢 ปกติ | X26: 6 | Y26: Maintenance Team | Z26: 7 | AA26: oversee
A27: 26 | B27: Forming | C27: Vacuum | D27: - | F27: All | G27: Electrical System | H27: PT-26 | I27: Overload Motor Vacuum | J27: B | M27: PCS | N27: 0 | O27: AR-26 | P27: 4 | Q27: 2 | R27: =ROUND(Q27*0.5,0) -> 1 | S27: =Q27+R27 -> 3 | T27: =SUMIF('Stock In Log'!C:C, H27, 'Stock In Log'!D:D) - SUMIF('Stock Out Log'!C:C, H27, 'Stock Out Log'!D:D) -> 2 | U27: =N27*T27 -> 0 | V27: =IF(T27<=0,"ควรสั่งซื้อ", IF(T27<=S27,"ควรสั่งซื้อ","ปกติ")) -> ควรสั่งซื้อ | W27: =IF(T27<=0, "🔴 วิกฤต! (ของหมด)", IF(T27<=S27, "🟡 ควรสั่งซื้อ (ต่ำกว่า ROP)", "🟢 ปกติ")) -> 🟡 ควรสั่งซื้อ (ต่ำกว่า ROP) | X27: 6 | Y27: Maintenance Team | Z27: 7 | AA27: oversee
A28: 27 | B28: Forming | C28: Vacuum | D28: - | G28: Electrical System | H28: PT-27 | I28: Relay | J28: A | K28: Omron | M28: PCS | N28: 0 | O28: AR-27 | P28: 0 | Q28: 0 | R28: =ROUND(Q28*0.5,0) -> 0 | S28: =Q28+R28 -> 0 | T28: =SUMIF('Stock In Log'!C:C, H28, 'Stock In Log'!D:D) - SUMIF('Stock Out Log'!C:C, H28, 'Stock Out Log'!D:D) -> 0 | U28: =N28*T28 -> 0 | V28: =IF(T28<=0,"ควรสั่งซื้อ", IF(T28<=S28,"ควรสั่งซื้อ","ปกติ")) -> ควรสั่งซื้อ | W28: =IF(T28<=0, "🔴 วิกฤต! (ของหมด)", IF(T28<=S28, "🟡 ควรสั่งซื้อ (ต่ำกว่า ROP)", "🟢 ปกติ")) -> 🔴 วิกฤต! (ของหมด) | X28: 9 | Y28: Maintenance Team | Z28: 0
A29: 28 | B29: Forming | C29: Vacuum | D29: - | F29: A4-A7,B4-B7 | G29: Electrical System | H29: PT-28 | I29: PLC Controller | J29: A | K29: Omron | M29: PCS | N29: 0 | O29: AR-28 | P29: 0 | Q29: 0 | R29: =ROUND(Q29*0.5,0) -> 0 | S29: =Q29+R29 -> 0 | T29: =SUMIF('Stock In Log'!C:C, H29, 'Stock In Log'!D:D) - SUMIF('Stock Out Log'!C:C, H29, 'Stock Out Log'!D:D) -> 0 | U29: =N29*T29 -> 0 | V29: =IF(T29<=0,"ควรสั่งซื้อ", IF(T29<=S29,"ควรสั่งซื้อ","ปกติ")) -> ควรสั่งซื้อ | W29: =IF(T29<=0, "🔴 วิกฤต! (ของหมด)", IF(T29<=S29, "🟡 ควรสั่งซื้อ (ต่ำกว่า ROP)", "🟢 ปกติ")) -> 🔴 วิกฤต! (ของหมด) | X29: 9 | Y29: Maintenance Team | Z29: 0
A30: 29 | B30: Forming | C30: Vacuum | D30: - | F30: A4-A7,B4-B7 | G30: Electrical System | H30: PT-29 | I30: PLC Controller | J30: A | K30: Omron | M30: PCS | N30: 0 | O30: AR-29 | P30: 0 | Q30: 0 | R30: =ROUND(Q30*0.5,0) -> 0 | S30: =Q30+R30 -> 0 | T30: =SUMIF('Stock In Log'!C:C, H30, 'Stock In Log'!D:D) - SUMIF('Stock Out Log'!C:C, H30, 'Stock Out Log'!D:D) -> 0 | U30: =N30*T30 -> 0 | V30: =IF(T30<=0,"ควรสั่งซื้อ", IF(T30<=S30,"ควรสั่งซื้อ","ปกติ")) -> ควรสั่งซื้อ | W30: =IF(T30<=0, "🔴 วิกฤต! (ของหมด)", IF(T30<=S30, "🟡 ควรสั่งซื้อ (ต่ำกว่า ROP)", "🟢 ปกติ")) -> 🔴 วิกฤต! (ของหมด) | X30: 9 | Y30: Maintenance Team | Z30: 0
A31: 30 | B31: Forming | C31: Vacuum | D31: - | F31: A4-A7,B4-B8 | G31: Electrical System | H31: PT-30 | I31: PLC Controller | J31: A | K31: Omron | M31: PCS | N31: 28000 | O31: AR-30 | P31: 0 | Q31: 0 | R31: =ROUND(Q31*0.5,0) -> 0 | S31: =Q31+R31 -> 0 | T31: =SUMIF('Stock In Log'!C:C, H31, 'Stock In Log'!D:D) - SUMIF('Stock Out Log'!C:C, H31, 'Stock Out Log'!D:D) -> 0 | U31: =N31*T31 -> 0 | V31: =IF(T31<=0,"ควรสั่งซื้อ", IF(T31<=S31,"ควรสั่งซื้อ","ปกติ")) -> ควรสั่งซื้อ | W31: =IF(T31<=0, "🔴 วิกฤต! (ของหมด)", IF(T31<=S31, "🟡 ควรสั่งซื้อ (ต่ำกว่า ROP)", "🟢 ปกติ")) -> 🔴 วิกฤต! (ของหมด) | X31: 9 | Y31: Maintenance Team | Z31: 0 | AB31: ศิวจักร์ 3000 บาท ค่าแรง
A32: 31 | B32: Forming | C32: Vacuum | D32: - | F32: A4-A7,B4-B7 | G32: Electrical System | H32: PT-31 | I32: PLC Controller | J32: A | K32: Omron | M32: PCS | N32: 0 | O32: AR-31 | P32: 0 | Q32: 0 | R32: =ROUND(Q32*0.5,0) -> 0 | S32: =Q32+R32 -> 0 | T32: =SUMIF('Stock In Log'!C:C, H32, 'Stock In Log'!D:D) - SUMIF('Stock Out Log'!C:C, H32, 'Stock Out Log'!D:D) -> 0 | U32: =N32*T32 -> 0 | V32: =IF(T32<=0,"ควรสั่งซื้อ", IF(T32<=S32,"ควรสั่งซื้อ","ปกติ")) -> ควรสั่งซื้อ | W32: =IF(T32<=0, "🔴 วิกฤต! (ของหมด)", IF(T32<=S32, "🟡 ควรสั่งซื้อ (ต่ำกว่า ROP)", "🟢 ปกติ")) -> 🔴 วิกฤต! (ของหมด) | X32: 9 | Y32: Maintenance Team | Z32: 0
A33: 32 | B33: Forming | C33: Vacuum | D33: - | F33: A4-A7,B4-B7 | G33: Electrical System | H33: PT-32 | I33: PLC Controller | J33: A | K33: Omron | M33: PCS | N33: 0 | O33: AR-32 | P33: 0 | Q33: 0 | R33: =ROUND(Q33*0.5,0) -> 0 | S33: =Q33+R33 -> 0 | T33: =SUMIF('Stock In Log'!C:C, H33, 'Stock In Log'!D:D) - SUMIF('Stock Out Log'!C:C, H33, 'Stock Out Log'!D:D) -> 0 | U33: =N33*T33 -> 0 | V33: =IF(T33<=0,"ควรสั่งซื้อ", IF(T33<=S33,"ควรสั่งซื้อ","ปกติ")) -> ควรสั่งซื้อ | W33: =IF(T33<=0, "🔴 วิกฤต! (ของหมด)", IF(T33<=S33, "🟡 ควรสั่งซื้อ (ต่ำกว่า ROP)", "🟢 ปกติ")) -> 🔴 วิกฤต! (ของหมด) | X33: 9 | Y33: Maintenance Team | Z33: 0
A34: 33 | B34: Forming | C34: Vacuum | D34: - | F34: All | G34: Electrical System | H34: PT-33 | I34: Touch Screen | J34: B | K34: Fuji | M34: PCS | N34: 0 | O34: AR-33 | P34: 0 | Q34: 0 | R34: =ROUND(Q34*0.5,0) -> 0 | S34: =Q34+R34 -> 0 | T34: =SUMIF('Stock In Log'!C:C, H34, 'Stock In Log'!D:D) - SUMIF('Stock Out Log'!C:C, H34, 'Stock Out Log'!D:D) -> 0 | U34: =N34*T34 -> 0 | V34: =IF(T34<=0,"ควรสั่งซื้อ", IF(T34<=S34,"ควรสั่งซื้อ","ปกติ")) -> ควรสั่งซื้อ | W34: =IF(T34<=0, "🔴 วิกฤต! (ของหมด)", IF(T34<=S34, "🟡 ควรสั่งซื้อ (ต่ำกว่า ROP)", "🟢 ปกติ")) -> 🔴 วิกฤต! (ของหมด) | X34: 6 | Y34: Maintenance Team | Z34: 0
A35: 34 | B35: Forming | C35: Vacuum | D35: - | F35: All | G35: Electrical System | H35: PT-34 | I35: Heater ( Top Plate) | J35: B | K35: Srang Sern | M35: PCS | N35: 0 | O35: AR-34 | P35: 3 | Q35: 2 | R35: =ROUND(Q35*0.5,0) -> 1 | S35: =Q35+R35 -> 3 | T35: =SUMIF('Stock In Log'!C:C, H35, 'Stock In Log'!D:D) - SUMIF('Stock Out Log'!C:C, H35, 'Stock Out Log'!D:D) -> 0 | U35: =N35*T35 -> 0 | V35: =IF(T35<=0,"ควรสั่งซื้อ", IF(T35<=S35,"ควรสั่งซื้อ","ปกติ")) -> ควรสั่งซื้อ | W35: =IF(T35<=0, "🔴 วิกฤต! (ของหมด)", IF(T35<=S35, "🟡 ควรสั่งซื้อ (ต่ำกว่า ROP)", "🟢 ปกติ")) -> 🔴 วิกฤต! (ของหมด) | X35: 6 | Y35: Maintenance Team | Z35: 45 | AA35: oversee
A36: 35 | B36: Forming | C36: Vacuum | D36: - | F36: All | G36: Electrical System | H36: PT-35 | I36: Heater(Top/Lower Plate ) | J36: B | K36: Srang Sern | M36: PCS | N36: 0 | O36: AR-35 | P36: 4 | Q36: 2 | R36: =ROUND(Q36*0.5,0) -> 1 | S36: =Q36+R36 -> 3 | T36: =SUMIF('Stock In Log'!C:C, H36, 'Stock In Log'!D:D) - SUMIF('Stock Out Log'!C:C, H36, 'Stock Out Log'!D:D) -> 1 | U36: =N36*T36 -> 0 | V36: =IF(T36<=0,"ควรสั่งซื้อ", IF(T36<=S36,"ควรสั่งซื้อ","ปกติ")) -> ควรสั่งซื้อ | W36: =IF(T36<=0, "🔴 วิกฤต! (ของหมด)", IF(T36<=S36, "🟡 ควรสั่งซื้อ (ต่ำกว่า ROP)", "🟢 ปกติ")) -> 🟡 ควรสั่งซื้อ (ต่ำกว่า ROP) | X36: 6 | Y36: Maintenance Team | Z36: 45 | AA36: oversee
A37: 36 | B37: Forming | C37: Vacuum | D37: - | F37: All | G37: Electrical System | H37: PT-36 | I37: Heater(Top/Lower Plate) | J37: B | K37: Srang Sern | M37: PCS | N37: 0 | O37: AR-36 | P37: 2 | Q37: 1 | R37: =ROUND(Q37*0.5,0) -> 1 | S37: =Q37+R37 -> 2 | T37: =SUMIF('Stock In Log'!C:C, H37, 'Stock In Log'!D:D) - SUMIF('Stock Out Log'!C:C, H37, 'Stock Out Log'!D:D) -> 1 | U37: =N37*T37 -> 0 | V37: =IF(T37<=0,"ควรสั่งซื้อ", IF(T37<=S37,"ควรสั่งซื้อ","ปกติ")) -> ควรสั่งซื้อ | W37: =IF(T37<=0, "🔴 วิกฤต! (ของหมด)", IF(T37<=S37, "🟡 ควรสั่งซื้อ (ต่ำกว่า ROP)", "🟢 ปกติ")) -> 🟡 ควรสั่งซื้อ (ต่ำกว่า ROP) | X37: 6 | Y37: Maintenance Team | Z37: 45 | AA37: oversee
A38: 37 | B38: Forming | C38: Vacuum | D38: - | F38: All | G38: Electrical System | H38: PT-37 | I38: Heater ( Top Plate) | J38: B | K38: Srang Sern | M38: PCS | N38: 0 | O38: AR-37 | P38: 2 | Q38: 1 | R38: =ROUND(Q38*0.5,0) -> 1 | S38: =Q38+R38 -> 2 | T38: =SUMIF('Stock In Log'!C:C, H38, 'Stock In Log'!D:D) - SUMIF('Stock Out Log'!C:C, H38, 'Stock Out Log'!D:D) -> 5 | U38: =N38*T38 -> 0 | V38: =IF(T38<=0,"ควรสั่งซื้อ", IF(T38<=S38,"ควรสั่งซื้อ","ปกติ")) -> ปกติ | W38: =IF(T38<=0, "🔴 วิกฤต! (ของหมด)", IF(T38<=S38, "🟡 ควรสั่งซื้อ (ต่ำกว่า ROP)", "🟢 ปกติ")) -> 🟢 ปกติ | X38: 6 | Y38: Maintenance Team | Z38: 45 | AA38: oversee
A39: 38 | B39: Forming | C39: Desma | D39: - | F39: D8,D10,D11 | G39: Top HEPL part | H39: PT-38 | I39: Insulating plate top 560 x630 S400HT | J39: B | K39: Desma | M39: PCS | N39: 12271 | O39: AR-38 | P39: 2 | Q39: 1 | R39: =ROUND(Q39*0.5,0) -> 1 | S39: =Q39+R39 -> 2 | T39: =SUMIF('Stock In Log'!C:C, H39, 'Stock In Log'!D:D) - SUMIF('Stock Out Log'!C:C, H39, 'Stock Out Log'!D:D) -> 0 | U39: =N39*T39 -> 0 | V39: =IF(T39<=0,"ควรสั่งซื้อ", IF(T39<=S39,"ควรสั่งซื้อ","ปกติ")) -> ควรสั่งซื้อ | W39: =IF(T39<=0, "🔴 วิกฤต! (ของหมด)", IF(T39<=S39, "🟡 ควรสั่งซื้อ (ต่ำกว่า ROP)", "🟢 ปกติ")) -> 🔴 วิกฤต! (ของหมด) | X39: 6 | Y39: Maintenance Team | Z39: 0 | AA39: oversee
A40: 39 | B40: Forming | C40: Desma | D40: - | F40: D8,D10,D11 | G40: Top HEPL part | H40: PT-39 | I40: Socket Head Screw M16x75 DiN 921-8.8 | J40: B | K40: Desma | M40: PCS | N40: 36.85 | O40: AR-39 | P40: 20 | Q40: 12 | R40: =ROUND(Q40*0.5,0) -> 6 | S40: =Q40+R40 -> 18 | T40: =SUMIF('Stock In Log'!C:C, H40, 'Stock In Log'!D:D) - SUMIF('Stock Out Log'!C:C, H40, 'Stock Out Log'!D:D) -> 0 | U40: =N40*T40 -> 0 | V40: =IF(T40<=0,"ควรสั่งซื้อ", IF(T40<=S40,"ควรสั่งซื้อ","ปกติ")) -> ควรสั่งซื้อ | W40: =IF(T40<=0, "🔴 วิกฤต! (ของหมด)", IF(T40<=S40, "🟡 ควรสั่งซื้อ (ต่ำกว่า ROP)", "🟢 ปกติ")) -> 🔴 วิกฤต! (ของหมด) | X40: 6 | Y40: Maintenance Team | Z40: 0 | AA40: oversee
A41: 40 | B41: Forming | C41: Desma | D41: - | F41: D8,D10,D11 | G41: Top HEPL part | H41: PT-40 | I41: Slotted Pan Heasd screw M4x8 DIN 921-5.8 | J41: B | K41: Desma | M41: PCS | N41: 36.85 | O41: AR-40 | P41: 2 | Q41: 1 | R41: =ROUND(Q41*0.5,0) -> 1 | S41: =Q41+R41 -> 2 | T41: =SUMIF('Stock In Log'!C:C, H41, 'Stock In Log'!D:D) - SUMIF('Stock Out Log'!C:C, H41, 'Stock Out Log'!D:D) -> 0 | U41: =N41*T41 -> 0 | V41: =IF(T41<=0,"ควรสั่งซื้อ", IF(T41<=S41,"ควรสั่งซื้อ","ปกติ")) -> ควรสั่งซื้อ | W41: =IF(T41<=0, "🔴 วิกฤต! (ของหมด)", IF(T41<=S41, "🟡 ควรสั่งซื้อ (ต่ำกว่า ROP)", "🟢 ปกติ")) -> 🔴 วิกฤต! (ของหมด) | X41: 6 | Y41: Maintenance Team | Z41: 0 | AA41: oversee | AB41: Local
A42: 41 | B42: Forming | C42: Desma | D42: - | F42: D8,D10,D11 | G42: Top HEPL part | H42: PT-41 | I42: Connecting Box HEPL 560 | J42: B | K42: Desma | M42: PCS | N42: 3685 | O42: AR-41 | P42: 2 | Q42: 1 | R42: =ROUND(Q42*0.5,0) -> 1 | S42: =Q42+R42 -> 2 | T42: =SUMIF('Stock In Log'!C:C, H42, 'Stock In Log'!D:D) - SUMIF('Stock Out Log'!C:C, H42, 'Stock Out Log'!D:D) -> 0 | U42: =N42*T42 -> 0 | V42: =IF(T42<=0,"ควรสั่งซื้อ", IF(T42<=S42,"ควรสั่งซื้อ","ปกติ")) -> ควรสั่งซื้อ | W42: =IF(T42<=0, "🔴 วิกฤต! (ของหมด)", IF(T42<=S42, "🟡 ควรสั่งซื้อ (ต่ำกว่า ROP)", "🟢 ปกติ")) -> 🔴 วิกฤต! (ของหมด) | X42: 6 | Y42: Maintenance Team | Z42: 0 | AA42: oversee | AB42: Local
A43: 42 | B43: Forming | C43: Desma | D43: - | F43: D8,D10,D11 | G43: Top HEPL part | H43: PT-42 | I43: Socket Head Screw M5x20 DiN 912- 12.9 | J43: B | K43: Desma | M43: PCS | N43: 36.85 | O43: AR-42 | P43: 2 | Q43: 1 | R43: =ROUND(Q43*0.5,0) -> 1 | S43: =Q43+R43 -> 2 | T43: =SUMIF('Stock In Log'!C:C, H43, 'Stock In Log'!D:D) - SUMIF('Stock Out Log'!C:C, H43, 'Stock Out Log'!D:D) -> 0 | U43: =N43*T43 -> 0 | V43: =IF(T43<=0,"ควรสั่งซื้อ", IF(T43<=S43,"ควรสั่งซื้อ","ปกติ")) -> ควรสั่งซื้อ | W43: =IF(T43<=0, "🔴 วิกฤต! (ของหมด)", IF(T43<=S43, "🟡 ควรสั่งซื้อ (ต่ำกว่า ROP)", "🟢 ปกติ")) -> 🔴 วิกฤต! (ของหมด) | X43: 6 | Y43: Maintenance Team | Z43: 0 | AA43: oversee | AB43: Local
A44: 43 | B44: Forming | C44: Desma | D44: - | F44: D8,D10,D11 | G44: Main Hyd. | H44: PT-43 | I44: DC Valve Hydrulic | J44: A | K44: Rexrath | M44: PCS | N44: 0 | O44: AR-43 | P44: 0 | Q44: 0 | R44: =ROUND(Q44*0.5,0) -> 0 | S44: =Q44+R44 -> 0 | T44: =SUMIF('Stock In Log'!C:C, H44, 'Stock In Log'!D:D) - SUMIF('Stock Out Log'!C:C, H44, 'Stock Out Log'!D:D) -> 0 | U44: =N44*T44 -> 0 | V44: =IF(T44<=0,"ควรสั่งซื้อ", IF(T44<=S44,"ควรสั่งซื้อ","ปกติ")) -> ควรสั่งซื้อ | W44: =IF(T44<=0, "🔴 วิกฤต! (ของหมด)", IF(T44<=S44, "🟡 ควรสั่งซื้อ (ต่ำกว่า ROP)", "🟢 ปกติ")) -> 🔴 วิกฤต! (ของหมด) | X44: 9 | Y44: Maintenance Team | Z44: 0
A45: 44 | B45: Forming | C45: Desma | D45: - | F45: D8,D10,D11 | G45: Main Hyd. | H45: PT-44 | I45: Counter Balance Valve | J45: A | K45: Rexrath | M45: PCS | N45: 0 | O45: AR-44 | P45: 0 | Q45: 0 | R45: =ROUND(Q45*0.5,0) -> 0 | S45: =Q45+R45 -> 0 | T45: =SUMIF('Stock In Log'!C:C, H45, 'Stock In Log'!D:D) - SUMIF('Stock Out Log'!C:C, H45, 'Stock Out Log'!D:D) -> 0 | U45: =N45*T45 -> 0 | V45: =IF(T45<=0,"ควรสั่งซื้อ", IF(T45<=S45,"ควรสั่งซื้อ","ปกติ")) -> ควรสั่งซื้อ | W45: =IF(T45<=0, "🔴 วิกฤต! (ของหมด)", IF(T45<=S45, "🟡 ควรสั่งซื้อ (ต่ำกว่า ROP)", "🟢 ปกติ")) -> 🔴 วิกฤต! (ของหมด) | X45: 9 | Y45: Maintenance Team | Z45: 0
A46: 45 | B46: Forming | C46: Desma | D46: - | F46: D8,D10,D11 | G46: Main Hyd. | H46: PT-45 | I46: Pres relief valve | J46: A | K46: Rexrath | M46: PCS | N46: 0 | O46: AR-45 | P46: 0 | Q46: 0 | R46: =ROUND(Q46*0.5,0) -> 0 | S46: =Q46+R46 -> 0 | T46: =SUMIF('Stock In Log'!C:C, H46, 'Stock In Log'!D:D) - SUMIF('Stock Out Log'!C:C, H46, 'Stock Out Log'!D:D) -> 0 | U46: =N46*T46 -> 0 | V46: =IF(T46<=0,"ควรสั่งซื้อ", IF(T46<=S46,"ควรสั่งซื้อ","ปกติ")) -> ควรสั่งซื้อ | W46: =IF(T46<=0, "🔴 วิกฤต! (ของหมด)", IF(T46<=S46, "🟡 ควรสั่งซื้อ (ต่ำกว่า ROP)", "🟢 ปกติ")) -> 🔴 วิกฤต! (ของหมด) | X46: 9 | Y46: Maintenance Team | Z46: 0
A47: 46 | B47: Extruder | C47: Extruder 01 | D47: EX-01 | G47: Hot Oven No.1,3,4 | H47: PT-46 | I47: Heater | J47: A | M47: PCS | N47: 0 | O47: AR-46 | P47: 5 | Q47: 3 | R47: =ROUND(Q47*0.5,0) -> 2 | S47: =Q47+R47 -> 5 | T47: =SUMIF('Stock In Log'!C:C, H47, 'Stock In Log'!D:D) - SUMIF('Stock Out Log'!C:C, H47, 'Stock Out Log'!D:D) -> 0 | U47: =N47*T47 -> 0 | V47: =IF(T47<=0,"ควรสั่งซื้อ", IF(T47<=S47,"ควรสั่งซื้อ","ปกติ")) -> ควรสั่งซื้อ | W47: =IF(T47<=0, "🔴 วิกฤต! (ของหมด)", IF(T47<=S47, "🟡 ควรสั่งซื้อ (ต่ำกว่า ROP)", "🟢 ปกติ")) -> 🔴 วิกฤต! (ของหมด) | X47: 9 | Y47: Maintenance Team | Z47: 0
A48: 47 | B48: Extruder | C48: Extruder 01 | D48: EX-01 | G48: Hot Oven No.2 | H48: PT-47 | I48: Heater | J48: A | M48: PCS | N48: 0 | O48: AR-47 | P48: 3 | Q48: 2 | R48: =ROUND(Q48*0.5,0) -> 1 | S48: =Q48+R48 -> 3 | T48: =SUMIF('Stock In Log'!C:C, H48, 'Stock In Log'!D:D) - SUMIF('Stock Out Log'!C:C, H48, 'Stock Out Log'!D:D) -> 1 | U48: =N48*T48 -> 0 | V48: =IF(T48<=0,"ควรสั่งซื้อ", IF(T48<=S48,"ควรสั่งซื้อ","ปกติ")) -> ควรสั่งซื้อ | W48: =IF(T48<=0, "🔴 วิกฤต! (ของหมด)", IF(T48<=S48, "🟡 ควรสั่งซื้อ (ต่ำกว่า ROP)", "🟢 ปกติ")) -> 🟡 ควรสั่งซื้อ (ต่ำกว่า ROP) | X48: 9 | Y48: Maintenance Team | Z48: 0
A49: 48 | B49: Extruder | C49: Extruder 01 | D49: EX-01 | G49: Hot Oven 1-4 | H49: PT-48 | I49: Motor Gear | J49: A | K49: Siemens | M49: PCS | N49: 0 | O49: AR-48 | P49: 2 | Q49: 1 | R49: =ROUND(Q49*0.5,0) -> 1 | S49: =Q49+R49 -> 2 | T49: =SUMIF('Stock In Log'!C:C, H49, 'Stock In Log'!D:D) - SUMIF('Stock Out Log'!C:C, H49, 'Stock Out Log'!D:D) -> 0 | U49: =N49*T49 -> 0 | V49: =IF(T49<=0,"ควรสั่งซื้อ", IF(T49<=S49,"ควรสั่งซื้อ","ปกติ")) -> ควรสั่งซื้อ | W49: =IF(T49<=0, "🔴 วิกฤต! (ของหมด)", IF(T49<=S49, "🟡 ควรสั่งซื้อ (ต่ำกว่า ROP)", "🟢 ปกติ")) -> 🔴 วิกฤต! (ของหมด) | X49: 9 | Y49: Maintenance Team | Z49: 0 | AB49: Actual 27 PC
A50: 49 | B50: Extruder | C50: Extruder 01 | D50: EX-01 | G50: Hot Oven 1-4 | H50: PT-49 | I50: Gear Unit | J50: A | K50: Hangzhou Wanjie | M50: PCS | N50: 0 | O50: AR-49 | P50: 2 | Q50: 1 | R50: =ROUND(Q50*0.5,0) -> 1 | S50: =Q50+R50 -> 2 | T50: =SUMIF('Stock In Log'!C:C, H50, 'Stock In Log'!D:D) - SUMIF('Stock Out Log'!C:C, H50, 'Stock Out Log'!D:D) -> 0 | U50: =N50*T50 -> 0 | V50: =IF(T50<=0,"ควรสั่งซื้อ", IF(T50<=S50,"ควรสั่งซื้อ","ปกติ")) -> ควรสั่งซื้อ | W50: =IF(T50<=0, "🔴 วิกฤต! (ของหมด)", IF(T50<=S50, "🟡 ควรสั่งซื้อ (ต่ำกว่า ROP)", "🟢 ปกติ")) -> 🔴 วิกฤต! (ของหมด) | X50: 9 | Y50: Maintenance Team | Z50: 0 | AB50: Actual 8 PC
A51: 50 | B51: Extruder | C51: Extruder 01 | D51: EX-01 | G51: Hot Oven 1-4 | H51: PT-50 | I51: Inverter | J51: A | K51: Delta | M51: PCS | N51: 0 | O51: AR-50 | P51: 2 | Q51: 1 | R51: =ROUND(Q51*0.5,0) -> 1 | S51: =Q51+R51 -> 2 | T51: =SUMIF('Stock In Log'!C:C, H51, 'Stock In Log'!D:D) - SUMIF('Stock Out Log'!C:C, H51, 'Stock Out Log'!D:D) -> 0 | U51: =N51*T51 -> 0 | V51: =IF(T51<=0,"ควรสั่งซื้อ", IF(T51<=S51,"ควรสั่งซื้อ","ปกติ")) -> ควรสั่งซื้อ | W51: =IF(T51<=0, "🔴 วิกฤต! (ของหมด)", IF(T51<=S51, "🟡 ควรสั่งซื้อ (ต่ำกว่า ROP)", "🟢 ปกติ")) -> 🔴 วิกฤต! (ของหมด) | X51: 9 | Y51: Maintenance Team | Z51: 0
A52: 51 | B52: Extruder | C52: Extruder 01 | D52: EX-01 | G52: Hot Oven 1-4 | H52: PT-51 | I52: Temp Control | J52: A | K52: "Omron" | M52: PCS | N52: 0 | O52: AR-51 | P52: 2 | Q52: 1 | R52: =ROUND(Q52*0.5,0) -> 1 | S52: =Q52+R52 -> 2 | T52: =SUMIF('Stock In Log'!C:C, H52, 'Stock In Log'!D:D) - SUMIF('Stock Out Log'!C:C, H52, 'Stock Out Log'!D:D) -> 0 | U52: =N52*T52 -> 0 | V52: =IF(T52<=0,"ควรสั่งซื้อ", IF(T52<=S52,"ควรสั่งซื้อ","ปกติ")) -> ควรสั่งซื้อ | W52: =IF(T52<=0, "🔴 วิกฤต! (ของหมด)", IF(T52<=S52, "🟡 ควรสั่งซื้อ (ต่ำกว่า ROP)", "🟢 ปกติ")) -> 🔴 วิกฤต! (ของหมด) | X52: 9 | Y52: Maintenance Team | Z52: 0
A53: 52 | B53: Extruder | C53: Extruder 01 | D53: EX-01 | G53: Hot Oven 1-4 | H53: PT-52 | I53: Motor Blower | J53: A | K53: Yangyi | M53: PCS | N53: 0 | O53: AR-52 | P53: 2 | Q53: 1 | R53: =ROUND(Q53*0.5,0) -> 1 | S53: =Q53+R53 -> 2 | T53: =SUMIF('Stock In Log'!C:C, H53, 'Stock In Log'!D:D) - SUMIF('Stock Out Log'!C:C, H53, 'Stock Out Log'!D:D) -> 0 | U53: =N53*T53 -> 0 | V53: =IF(T53<=0,"ควรสั่งซื้อ", IF(T53<=S53,"ควรสั่งซื้อ","ปกติ")) -> ควรสั่งซื้อ | W53: =IF(T53<=0, "🔴 วิกฤต! (ของหมด)", IF(T53<=S53, "🟡 ควรสั่งซื้อ (ต่ำกว่า ROP)", "🟢 ปกติ")) -> 🔴 วิกฤต! (ของหมด) | X53: 9 | Y53: Maintenance Team | Z53: 0
A54: 53 | B54: Extruder | C54: Extruder 01 | D54: EX-01 | G54: Hot Oven 1-4 | H54: PT-53 | I54: Thermo | J54: A | K54: Misumi | M54: PCS | N54: 0 | O54: AR-53 | P54: 0 | Q54: 0 | R54: =ROUND(Q54*0.5,0) -> 0 | S54: =Q54+R54 -> 0 | T54: =SUMIF('Stock In Log'!C:C, H54, 'Stock In Log'!D:D) - SUMIF('Stock Out Log'!C:C, H54, 'Stock Out Log'!D:D) -> 0 | U54: =N54*T54 -> 0 | V54: =IF(T54<=0,"ควรสั่งซื้อ", IF(T54<=S54,"ควรสั่งซื้อ","ปกติ")) -> ควรสั่งซื้อ | W54: =IF(T54<=0, "🔴 วิกฤต! (ของหมด)", IF(T54<=S54, "🟡 ควรสั่งซื้อ (ต่ำกว่า ROP)", "🟢 ปกติ")) -> 🔴 วิกฤต! (ของหมด) | X54: 9 | Y54: Maintenance Team | Z54: 0
A55: 54 | B55: Extruder | C55: Extruder 01 | D55: EX-01 | G55: Hot Oven 1-4 | H55: PT-54 | I55: Toggle Sw. | J55: B | M55: PCS | N55: 0 | O55: AR-54 | P55: 3 | Q55: 2 | R55: =ROUND(Q55*0.5,0) -> 1 | S55: =Q55+R55 -> 3 | T55: =SUMIF('Stock In Log'!C:C, H55, 'Stock In Log'!D:D) - SUMIF('Stock Out Log'!C:C, H55, 'Stock Out Log'!D:D) -> 0 | U55: =N55*T55 -> 0 | V55: =IF(T55<=0,"ควรสั่งซื้อ", IF(T55<=S55,"ควรสั่งซื้อ","ปกติ")) -> ควรสั่งซื้อ | W55: =IF(T55<=0, "🔴 วิกฤต! (ของหมด)", IF(T55<=S55, "🟡 ควรสั่งซื้อ (ต่ำกว่า ROP)", "🟢 ปกติ")) -> 🔴 วิกฤต! (ของหมด) | X55: 6 | Y55: Maintenance Team | Z55: 0
A56: 55 | B56: Extruder | C56: Extruder 01 | D56: EX-01 | G56: Hot Oven 1-4 | H56: PT-55 | I56: Speed Control | J56: A | K56: Omron | M56: PCS | N56: 0 | O56: AR-55 | P56: 0 | Q56: 0 | R56: =ROUND(Q56*0.5,0) -> 0 | S56: =Q56+R56 -> 0 | T56: =SUMIF('Stock In Log'!C:C, H56, 'Stock In Log'!D:D) - SUMIF('Stock Out Log'!C:C, H56, 'Stock Out Log'!D:D) -> 0 | U56: =N56*T56 -> 0 | V56: =IF(T56<=0,"ควรสั่งซื้อ", IF(T56<=S56,"ควรสั่งซื้อ","ปกติ")) -> ควรสั่งซื้อ | W56: =IF(T56<=0, "🔴 วิกฤต! (ของหมด)", IF(T56<=S56, "🟡 ควรสั่งซื้อ (ต่ำกว่า ROP)", "🟢 ปกติ")) -> 🔴 วิกฤต! (ของหมด) | X56: 9 | Y56: Maintenance Team | Z56: 0
A57: 56 | B57: Extruder | C57: Extruder 01 | D57: EX-01 | G57: Hot Oven 1-4 | H57: PT-56 | I57: Speed Indicator | M57: PCS | N57: 0 | O57: AR-56 | P57: 3 | Q57: 2 | R57: =ROUND(Q57*0.5,0) -> 1 | S57: =Q57+R57 -> 3 | T57: =SUMIF('Stock In Log'!C:C, H57, 'Stock In Log'!D:D) - SUMIF('Stock Out Log'!C:C, H57, 'Stock Out Log'!D:D) -> 0 | U57: =N57*T57 -> 0 | V57: =IF(T57<=0,"ควรสั่งซื้อ", IF(T57<=S57,"ควรสั่งซื้อ","ปกติ")) -> ควรสั่งซื้อ | W57: =IF(T57<=0, "🔴 วิกฤต! (ของหมด)", IF(T57<=S57, "🟡 ควรสั่งซื้อ (ต่ำกว่า ROP)", "🟢 ปกติ")) -> 🔴 วิกฤต! (ของหมด) | X57: 3 | Y57: Store Keeper | Z57: 0
A58: 57 | B58: Extruder | C58: Extruder 01 | D58: EX-01 | G58: Hot Oven 1-4 | H58: PT-57 | I58: Conveyor belt tensioning shaft and guide rail | J58: A | M58: PCS | N58: 0 | O58: AR-57 | P58: 3 | Q58: 2 | R58: =ROUND(Q58*0.5,0) -> 1 | S58: =Q58+R58 -> 3 | T58: =SUMIF('Stock In Log'!C:C, H58, 'Stock In Log'!D:D) - SUMIF('Stock Out Log'!C:C, H58, 'Stock Out Log'!D:D) -> 0 | U58: =N58*T58 -> 0 | V58: =IF(T58<=0,"ควรสั่งซื้อ", IF(T58<=S58,"ควรสั่งซื้อ","ปกติ")) -> ควรสั่งซื้อ | W58: =IF(T58<=0, "🔴 วิกฤต! (ของหมด)", IF(T58<=S58, "🟡 ควรสั่งซื้อ (ต่ำกว่า ROP)", "🟢 ปกติ")) -> 🔴 วิกฤต! (ของหมด) | X58: 9 | Y58: Maintenance Team | Z58: 0
A59: 58 | B59: Extruder | C59: Extruder 01 | D59: EX-01 | G59: Hot Oven No.2 | H59: PT-58 | I59: Solid state | J59: B | K59: Fotek | M59: PCS | N59: 0 | O59: AR-58 | P59: 5 | Q59: 2 | R59: =ROUND(Q59*0.5,0) -> 1 | S59: =Q59+R59 -> 3 | T59: =SUMIF('Stock In Log'!C:C, H59, 'Stock In Log'!D:D) - SUMIF('Stock Out Log'!C:C, H59, 'Stock Out Log'!D:D) -> 5 | U59: =N59*T59 -> 0 | V59: =IF(T59<=0,"ควรสั่งซื้อ", IF(T59<=S59,"ควรสั่งซื้อ","ปกติ")) -> ปกติ | W59: =IF(T59<=0, "🔴 วิกฤต! (ของหมด)", IF(T59<=S59, "🟡 ควรสั่งซื้อ (ต่ำกว่า ROP)", "🟢 ปกติ")) -> 🟢 ปกติ | X59: 6 | Y59: Maintenance Team | Z59: 14 | AA59: oversee
A60: 59 | B60: Extruder | C60: Extruder 01 | D60: EX-01 | G60: Hot Oven No.1,3,4 | H60: PT-59 | I60: Solid state | J60: B | K60: Fotek | M60: PCS | N60: 0 | O60: AR-59 | P60: 6 | Q60: 3 | R60: =ROUND(Q60*0.5,0) -> 2 | S60: =Q60+R60 -> 5 | T60: =SUMIF('Stock In Log'!C:C, H60, 'Stock In Log'!D:D) - SUMIF('Stock Out Log'!C:C, H60, 'Stock Out Log'!D:D) -> 3 | U60: =N60*T60 -> 0 | V60: =IF(T60<=0,"ควรสั่งซื้อ", IF(T60<=S60,"ควรสั่งซื้อ","ปกติ")) -> ควรสั่งซื้อ | W60: =IF(T60<=0, "🔴 วิกฤต! (ของหมด)", IF(T60<=S60, "🟡 ควรสั่งซื้อ (ต่ำกว่า ROP)", "🟢 ปกติ")) -> 🟡 ควรสั่งซื้อ (ต่ำกว่า ROP) | X60: 6 | Y60: Maintenance Team | Z60: 14 | AA60: oversee
A61: 60 | B61: Extruder | C61: Extruder 01 | D61: EX-01 | G61: Hot Oven 1-4 | H61: PT-60 | I61: Magnetic | J61: B | K61: Fuji | M61: PCS | N61: 0 | O61: AR-60 | P61: 6 | Q61: 4 | R61: =ROUND(Q61*0.5,0) -> 2 | S61: =Q61+R61 -> 6 | T61: =SUMIF('Stock In Log'!C:C, H61, 'Stock In Log'!D:D) - SUMIF('Stock Out Log'!C:C, H61, 'Stock Out Log'!D:D) -> 4 | U61: =N61*T61 -> 0 | V61: =IF(T61<=0,"ควรสั่งซื้อ", IF(T61<=S61,"ควรสั่งซื้อ","ปกติ")) -> ควรสั่งซื้อ | W61: =IF(T61<=0, "🔴 วิกฤต! (ของหมด)", IF(T61<=S61, "🟡 ควรสั่งซื้อ (ต่ำกว่า ROP)", "🟢 ปกติ")) -> 🟡 ควรสั่งซื้อ (ต่ำกว่า ROP) | X61: 6 | Y61: Maintenance Team | Z61: 0
A62: 61 | B62: Extruder | C62: Extruder 01 | D62: EX-01 | G62: Hot Oven 1-4 | H62: PT-61 | I62: Over load | J62: A | K62: Fuji | M62: PCS | N62: 0 | O62: AR-61 | P62: 3 | Q62: 2 | R62: =ROUND(Q62*0.5,0) -> 1 | S62: =Q62+R62 -> 3 | T62: =SUMIF('Stock In Log'!C:C, H62, 'Stock In Log'!D:D) - SUMIF('Stock Out Log'!C:C, H62, 'Stock Out Log'!D:D) -> 0 | U62: =N62*T62 -> 0 | V62: =IF(T62<=0,"ควรสั่งซื้อ", IF(T62<=S62,"ควรสั่งซื้อ","ปกติ")) -> ควรสั่งซื้อ | W62: =IF(T62<=0, "🔴 วิกฤต! (ของหมด)", IF(T62<=S62, "🟡 ควรสั่งซื้อ (ต่ำกว่า ROP)", "🟢 ปกติ")) -> 🔴 วิกฤต! (ของหมด) | X62: 9 | Y62: Maintenance Team | Z62: 0
A63: 62 | B63: Extruder | C63: Extruder 01 | D63: EX-01 | G63: Hot Oven 1-4 | H63: PT-62 | I63: Breaker Main/Heater | J63: A | K63: Mitsubishi | M63: PCS | N63: 0 | O63: AR-62 | P63: 3 | Q63: 2 | R63: =ROUND(Q63*0.5,0) -> 1 | S63: =Q63+R63 -> 3 | T63: =SUMIF('Stock In Log'!C:C, H63, 'Stock In Log'!D:D) - SUMIF('Stock Out Log'!C:C, H63, 'Stock Out Log'!D:D) -> 0 | U63: =N63*T63 -> 0 | V63: =IF(T63<=0,"ควรสั่งซื้อ", IF(T63<=S63,"ควรสั่งซื้อ","ปกติ")) -> ควรสั่งซื้อ | W63: =IF(T63<=0, "🔴 วิกฤต! (ของหมด)", IF(T63<=S63, "🟡 ควรสั่งซื้อ (ต่ำกว่า ROP)", "🟢 ปกติ")) -> 🔴 วิกฤต! (ของหมด) | X63: 9 | Y63: Maintenance Team | Z63: 0 | AB63: 12 PC
A64: 63 | B64: Extruder | C64: Extruder 01 | D64: EX-01 | G64: Hot Oven 1-4 | H64: PT-63 | I64: Breaker | J64: A | K64: Mitsubishi | M64: PCS | N64: 0 | O64: AR-63 | P64: 3 | Q64: 2 | R64: =ROUND(Q64*0.5,0) -> 1 | S64: =Q64+R64 -> 3 | T64: =SUMIF('Stock In Log'!C:C, H64, 'Stock In Log'!D:D) - SUMIF('Stock Out Log'!C:C, H64, 'Stock Out Log'!D:D) -> 0 | U64: =N64*T64 -> 0 | V64: =IF(T64<=0,"ควรสั่งซื้อ", IF(T64<=S64,"ควรสั่งซื้อ","ปกติ")) -> ควรสั่งซื้อ | W64: =IF(T64<=0, "🔴 วิกฤต! (ของหมด)", IF(T64<=S64, "🟡 ควรสั่งซื้อ (ต่ำกว่า ROP)", "🟢 ปกติ")) -> 🔴 วิกฤต! (ของหมด) | X64: 9 | Y64: Maintenance Team | Z64: 0
A65: 64 | B65: Extruder | C65: Extruder 01 | D65: EX-01 | G65: Hot Oven 1-4 | H65: PT-64 | I65: Breaker Motor Blower /Inverter | J65: A | K65: Mitsubishi | M65: PCS | N65: 0 | O65: AR-64 | P65: 3 | Q65: 2 | R65: =ROUND(Q65*0.5,0) -> 1 | S65: =Q65+R65 -> 3 | T65: =SUMIF('Stock In Log'!C:C, H65, 'Stock In Log'!D:D) - SUMIF('Stock Out Log'!C:C, H65, 'Stock Out Log'!D:D) -> 0 | U65: =N65*T65 -> 0 | V65: =IF(T65<=0,"ควรสั่งซื้อ", IF(T65<=S65,"ควรสั่งซื้อ","ปกติ")) -> ควรสั่งซื้อ | W65: =IF(T65<=0, "🔴 วิกฤต! (ของหมด)", IF(T65<=S65, "🟡 ควรสั่งซื้อ (ต่ำกว่า ROP)", "🟢 ปกติ")) -> 🔴 วิกฤต! (ของหมด) | X65: 9 | Y65: Maintenance Team | Z65: 0 | AB65: 16 PC
A66: 65 | B66: Extruder | C66: Extruder 01 | D66: EX-01 | G66: Hot Oven 2-4 | H66: PT-65 | I66: Belt | J66: A | K66: ซันโตซ๊ | M66: PCS | N66: 9000 | O66: AR-65 | P66: 3 | Q66: 2 | R66: =ROUND(Q66*0.5,0) -> 1 | S66: =Q66+R66 -> 3 | T66: =SUMIF('Stock In Log'!C:C, H66, 'Stock In Log'!D:D) - SUMIF('Stock Out Log'!C:C, H66, 'Stock Out Log'!D:D) -> 1 | U66: =N66*T66 -> 9000 | V66: =IF(T66<=0,"ควรสั่งซื้อ", IF(T66<=S66,"ควรสั่งซื้อ","ปกติ")) -> ควรสั่งซื้อ | W66: =IF(T66<=0, "🔴 วิกฤต! (ของหมด)", IF(T66<=S66, "🟡 ควรสั่งซื้อ (ต่ำกว่า ROP)", "🟢 ปกติ")) -> 🟡 ควรสั่งซื้อ (ต่ำกว่า ROP) | X66: 9 | Y66: Maintenance Team | Z66: 5
A67: 66 | B67: Extruder | C67: Extruder 01 | D67: EX-01 | G67: Hot Oven 1-4 | H67: PT-66 | I67: Chain | J67: A | M67: PCS | N67: 0 | O67: AR-66 | P67: 2 | Q67: 1 | R67: =ROUND(Q67*0.5,0) -> 1 | S67: =Q67+R67 -> 2 | T67: =SUMIF('Stock In Log'!C:C, H67, 'Stock In Log'!D:D) - SUMIF('Stock Out Log'!C:C, H67, 'Stock Out Log'!D:D) -> 0 | U67: =N67*T67 -> 0 | V67: =IF(T67<=0,"ควรสั่งซื้อ", IF(T67<=S67,"ควรสั่งซื้อ","ปกติ")) -> ควรสั่งซื้อ | W67: =IF(T67<=0, "🔴 วิกฤต! (ของหมด)", IF(T67<=S67, "🟡 ควรสั่งซื้อ (ต่ำกว่า ROP)", "🟢 ปกติ")) -> 🔴 วิกฤต! (ของหมด) | X67: 9 | Y67: Maintenance Team | Z67: 0
A68: 67 | B68: Extruder | C68: Extruder 01 | D68: EX-01 | G68: Hot Oven 1-4 | H68: PT-67 | I68: Selector Switch | J68: B | K68: IDEC | M68: PCS | N68: 0 | O68: AR-67 | P68: 7 | Q68: 5 | R68: =ROUND(Q68*0.5,0) -> 3 | S68: =Q68+R68 -> 8 | T68: =SUMIF('Stock In Log'!C:C, H68, 'Stock In Log'!D:D) - SUMIF('Stock Out Log'!C:C, H68, 'Stock Out Log'!D:D) -> 0 | U68: =N68*T68 -> 0 | V68: =IF(T68<=0,"ควรสั่งซื้อ", IF(T68<=S68,"ควรสั่งซื้อ","ปกติ")) -> ควรสั่งซื้อ | W68: =IF(T68<=0, "🔴 วิกฤต! (ของหมด)", IF(T68<=S68, "🟡 ควรสั่งซื้อ (ต่ำกว่า ROP)", "🟢 ปกติ")) -> 🔴 วิกฤต! (ของหมด) | X68: 6 | Y68: Maintenance Team | Z68: 0
A69: 68 | B69: Extruder | C69: Extruder 01 | D69: EX-01 | G69: 'Pull Machine | H69: PT-68 | I69: Inverter | J69: A | K69: Delta | M69: PCS | N69: 0 | O69: AR-68 | P69: 2 | Q69: 1 | R69: =ROUND(Q69*0.5,0) -> 1 | S69: =Q69+R69 -> 2 | T69: =SUMIF('Stock In Log'!C:C, H69, 'Stock In Log'!D:D) - SUMIF('Stock Out Log'!C:C, H69, 'Stock Out Log'!D:D) -> 0 | U69: =N69*T69 -> 0 | V69: =IF(T69<=0,"ควรสั่งซื้อ", IF(T69<=S69,"ควรสั่งซื้อ","ปกติ")) -> ควรสั่งซื้อ | W69: =IF(T69<=0, "🔴 วิกฤต! (ของหมด)", IF(T69<=S69, "🟡 ควรสั่งซื้อ (ต่ำกว่า ROP)", "🟢 ปกติ")) -> 🔴 วิกฤต! (ของหมด) | X69: 9 | Y69: Maintenance Team | Z69: 0
A70: 69 | B70: Extruder | C70: Extruder 01 | D70: EX-01 | G70: 'Pull Machine | H70: PT-69 | I70: Motor | J70: A | K70: Siemens | M70: PCS | N70: 0 | O70: AR-69 | P70: 2 | Q70: 1 | R70: =ROUND(Q70*0.5,0) -> 1 | S70: =Q70+R70 -> 2 | T70: =SUMIF('Stock In Log'!C:C, H70, 'Stock In Log'!D:D) - SUMIF('Stock Out Log'!C:C, H70, 'Stock Out Log'!D:D) -> 0 | U70: =N70*T70 -> 0 | V70: =IF(T70<=0,"ควรสั่งซื้อ", IF(T70<=S70,"ควรสั่งซื้อ","ปกติ")) -> ควรสั่งซื้อ | W70: =IF(T70<=0, "🔴 วิกฤต! (ของหมด)", IF(T70<=S70, "🟡 ควรสั่งซื้อ (ต่ำกว่า ROP)", "🟢 ปกติ")) -> 🔴 วิกฤต! (ของหมด) | X70: 9 | Y70: Maintenance Team | Z70: 0
A71: 70 | B71: Extruder | C71: Extruder 01 | D71: EX-01 | G71: 'Pull Machine | H71: PT-70 | I71: Gear Unit | J71: A | K71: Hangzhou Wanjie | M71: PCS | N71: 0 | O71: AR-70 | P71: 0 | Q71: 0 | R71: =ROUND(Q71*0.5,0) -> 0 | S71: =Q71+R71 -> 0 | T71: =SUMIF('Stock In Log'!C:C, H71, 'Stock In Log'!D:D) - SUMIF('Stock Out Log'!C:C, H71, 'Stock Out Log'!D:D) -> 0 | U71: =N71*T71 -> 0 | V71: =IF(T71<=0,"ควรสั่งซื้อ", IF(T71<=S71,"ควรสั่งซื้อ","ปกติ")) -> ควรสั่งซื้อ | W71: =IF(T71<=0, "🔴 วิกฤต! (ของหมด)", IF(T71<=S71, "🟡 ควรสั่งซื้อ (ต่ำกว่า ROP)", "🟢 ปกติ")) -> 🔴 วิกฤต! (ของหมด) | X71: 9 | Y71: Maintenance Team | Z71: 0
A72: 71 | B72: Extruder | C72: Extruder 01 | D72: EX-01 | G72: Cutting Machine | H72: PT-71 | I72: Servo Amp | J72: A | K72: Delta | M72: PCS | N72: 0 | O72: AR-71 | P72: 1 | Q72: 1 | R72: =ROUND(Q72*0.5,0) -> 1 | S72: =Q72+R72 -> 2 | T72: =SUMIF('Stock In Log'!C:C, H72, 'Stock In Log'!D:D) - SUMIF('Stock Out Log'!C:C, H72, 'Stock Out Log'!D:D) -> 0 | U72: =N72*T72 -> 0 | V72: =IF(T72<=0,"ควรสั่งซื้อ", IF(T72<=S72,"ควรสั่งซื้อ","ปกติ")) -> ควรสั่งซื้อ | W72: =IF(T72<=0, "🔴 วิกฤต! (ของหมด)", IF(T72<=S72, "🟡 ควรสั่งซื้อ (ต่ำกว่า ROP)", "🟢 ปกติ")) -> 🔴 วิกฤต! (ของหมด) | X72: 9 | Y72: Maintenance Team | Z72: 0
A73: 72 | B73: Extruder | C73: Extruder 01 | D73: EX-01 | G73: Cutting Machine | H73: PT-72 | I73: AC Servo Motor | J73: A | K73: Delta | M73: PCS | N73: 0 | O73: AR-72 | P73: 1 | Q73: 1 | R73: =ROUND(Q73*0.5,0) -> 1 | S73: =Q73+R73 -> 2 | T73: =SUMIF('Stock In Log'!C:C, H73, 'Stock In Log'!D:D) - SUMIF('Stock Out Log'!C:C, H73, 'Stock Out Log'!D:D) -> 0 | U73: =N73*T73 -> 0 | V73: =IF(T73<=0,"ควรสั่งซื้อ", IF(T73<=S73,"ควรสั่งซื้อ","ปกติ")) -> ควรสั่งซื้อ | W73: =IF(T73<=0, "🔴 วิกฤต! (ของหมด)", IF(T73<=S73, "🟡 ควรสั่งซื้อ (ต่ำกว่า ROP)", "🟢 ปกติ")) -> 🔴 วิกฤต! (ของหมด) | X73: 9 | Y73: Maintenance Team | Z73: 0
A74: 73 | B74: Extruder | C74: Extruder 01 | D74: EX-01 | G74: Water Bath Unit | H74: PT-73 | I74: Motor Blower | J74: A | K74: Shanghai Full electrica | M74: PCS | N74: 0 | O74: AR-73 | P74: 1 | Q74: 1 | R74: =ROUND(Q74*0.5,0) -> 1 | S74: =Q74+R74 -> 2 | T74: =SUMIF('Stock In Log'!C:C, H74, 'Stock In Log'!D:D) - SUMIF('Stock Out Log'!C:C, H74, 'Stock Out Log'!D:D) -> 0 | U74: =N74*T74 -> 0 | V74: =IF(T74<=0,"ควรสั่งซื้อ", IF(T74<=S74,"ควรสั่งซื้อ","ปกติ")) -> ควรสั่งซื้อ | W74: =IF(T74<=0, "🔴 วิกฤต! (ของหมด)", IF(T74<=S74, "🟡 ควรสั่งซื้อ (ต่ำกว่า ROP)", "🟢 ปกติ")) -> 🔴 วิกฤต! (ของหมด) | X74: 9 | Y74: Maintenance Team | Z74: 0
A75: 74 | B75: Mixing | C75: Mix-55L | D75: Mix-01 | G75: Knewder Unit | H75: PT-74 | I75: Motor | J75: A | M75: PCS | N75: 0 | O75: AR-74 | P75: 1 | Q75: 1 | R75: =ROUND(Q75*0.5,0) -> 1 | S75: =Q75+R75 -> 2 | T75: =SUMIF('Stock In Log'!C:C, H75, 'Stock In Log'!D:D) - SUMIF('Stock Out Log'!C:C, H75, 'Stock Out Log'!D:D) -> 0 | U75: =N75*T75 -> 0 | V75: =IF(T75<=0,"ควรสั่งซื้อ", IF(T75<=S75,"ควรสั่งซื้อ","ปกติ")) -> ควรสั่งซื้อ | W75: =IF(T75<=0, "🔴 วิกฤต! (ของหมด)", IF(T75<=S75, "🟡 ควรสั่งซื้อ (ต่ำกว่า ROP)", "🟢 ปกติ")) -> 🔴 วิกฤต! (ของหมด) | X75: 9 | Y75: Maintenance Team | Z75: 0
A76: 75 | B76: Mixing | C76: Mix-55L | D76: Mix-01 | G76: Caleder | H76: PT-75 | I76: Motor | J76: A | M76: PCS | N76: 0 | O76: AR-75 | P76: 1 | Q76: 1 | R76: =ROUND(Q76*0.5,0) -> 1 | S76: =Q76+R76 -> 2 | T76: =SUMIF('Stock In Log'!C:C, H76, 'Stock In Log'!D:D) - SUMIF('Stock Out Log'!C:C, H76, 'Stock Out Log'!D:D) -> 0 | U76: =N76*T76 -> 0 | V76: =IF(T76<=0,"ควรสั่งซื้อ", IF(T76<=S76,"ควรสั่งซื้อ","ปกติ")) -> ควรสั่งซื้อ | W76: =IF(T76<=0, "🔴 วิกฤต! (ของหมด)", IF(T76<=S76, "🟡 ควรสั่งซื้อ (ต่ำกว่า ROP)", "🟢 ปกติ")) -> 🔴 วิกฤต! (ของหมด) | X76: 9 | Y76: Maintenance Team | Z76: 0
A77: 76 | B77: Mixing | C77: Mix-75L | D77: Mix-02 | G77: Knewder Unit | H77: PT-76 | I77: Motor | J77: A | M77: PCS | N77: 0 | O77: AR-76 | P77: 1 | Q77: 1 | R77: =ROUND(Q77*0.5,0) -> 1 | S77: =Q77+R77 -> 2 | T77: =SUMIF('Stock In Log'!C:C, H77, 'Stock In Log'!D:D) - SUMIF('Stock Out Log'!C:C, H77, 'Stock Out Log'!D:D) -> 0 | U77: =N77*T77 -> 0 | V77: =IF(T77<=0,"ควรสั่งซื้อ", IF(T77<=S77,"ควรสั่งซื้อ","ปกติ")) -> ควรสั่งซื้อ | W77: =IF(T77<=0, "🔴 วิกฤต! (ของหมด)", IF(T77<=S77, "🟡 ควรสั่งซื้อ (ต่ำกว่า ROP)", "🟢 ปกติ")) -> 🔴 วิกฤต! (ของหมด) | X77: 9 | Y77: Maintenance Team | Z77: 0
A78: 77 | B78: Mixing | C78: Mix-75L | D78: Mix-02 | G78: Caleder | H78: PT-77 | I78: Motor | J78: A | M78: PCS | N78: 0 | O78: AR-77 | P78: 1 | Q78: 1 | R78: =ROUND(Q78*0.5,0) -> 1 | S78: =Q78+R78 -> 2 | T78: =SUMIF('Stock In Log'!C:C, H78, 'Stock In Log'!D:D) - SUMIF('Stock Out Log'!C:C, H78, 'Stock Out Log'!D:D) -> 0 | U78: =N78*T78 -> 0 | V78: =IF(T78<=0,"ควรสั่งซื้อ", IF(T78<=S78,"ควรสั่งซื้อ","ปกติ")) -> ควรสั่งซื้อ | W78: =IF(T78<=0, "🔴 วิกฤต! (ของหมด)", IF(T78<=S78, "🟡 ควรสั่งซื้อ (ต่ำกว่า ROP)", "🟢 ปกติ")) -> 🔴 วิกฤต! (ของหมด) | X78: 6 | Y78: Maintenance Team | Z78: 0
A79: 78 | B79: Mixing | C79: Auto-Cut | D79: Cut-01 | G79: Electrical System | H79: PT-78 | I79: PLC Controller | J79: B | M79: PCS | N79: 0 | O79: AR-78 | P79: 1 | Q79: 1 | R79: =ROUND(Q79*0.5,0) -> 1 | S79: =Q79+R79 -> 2 | T79: =SUMIF('Stock In Log'!C:C, H79, 'Stock In Log'!D:D) - SUMIF('Stock Out Log'!C:C, H79, 'Stock Out Log'!D:D) -> 0 | U79: =N79*T79 -> 0 | V79: =IF(T79<=0,"ควรสั่งซื้อ", IF(T79<=S79,"ควรสั่งซื้อ","ปกติ")) -> ควรสั่งซื้อ | W79: =IF(T79<=0, "🔴 วิกฤต! (ของหมด)", IF(T79<=S79, "🟡 ควรสั่งซื้อ (ต่ำกว่า ROP)", "🟢 ปกติ")) -> 🔴 วิกฤต! (ของหมด) | X79: 6 | Y79: Maintenance Team | Z79: 0
A80: 79 | B80: Mixing | C80: Auto-Cut | D80: Cut-01 | G80: Pneumatic | H80: PT-79 | I80: Vavle | J80: B | M80: PCS | N80: 0 | O80: AR-79 | P80: 1 | Q80: 1 | R80: =ROUND(Q80*0.5,0) -> 1 | S80: =Q80+R80 -> 2 | T80: =SUMIF('Stock In Log'!C:C, H80, 'Stock In Log'!D:D) - SUMIF('Stock Out Log'!C:C, H80, 'Stock Out Log'!D:D) -> 0 | U80: =N80*T80 -> 0 | V80: =IF(T80<=0,"ควรสั่งซื้อ", IF(T80<=S80,"ควรสั่งซื้อ","ปกติ")) -> ควรสั่งซื้อ | W80: =IF(T80<=0, "🔴 วิกฤต! (ของหมด)", IF(T80<=S80, "🟡 ควรสั่งซื้อ (ต่ำกว่า ROP)", "🟢 ปกติ")) -> 🔴 วิกฤต! (ของหมด) | X80: 6 | Y80: Maintenance Team | Z80: 0
A81: 80 | B81: Auto slit | C81: Auto-Cut | D81: Slit-01 | G81: Pneumatic | H81: PT-80 | I81: Vavle | J81: B | M81: PCS | N81: 0 | O81: AR-80 | P81: 1 | Q81: 1 | R81: =ROUND(Q81*0.5,0) -> 1 | S81: =Q81+R81 -> 2 | T81: =SUMIF('Stock In Log'!C:C, H81, 'Stock In Log'!D:D) - SUMIF('Stock Out Log'!C:C, H81, 'Stock Out Log'!D:D) -> 0 | U81: =N81*T81 -> 0 | V81: =IF(T81<=0,"ควรสั่งซื้อ", IF(T81<=S81,"ควรสั่งซื้อ","ปกติ")) -> ควรสั่งซื้อ | W81: =IF(T81<=0, "🔴 วิกฤต! (ของหมด)", IF(T81<=S81, "🟡 ควรสั่งซื้อ (ต่ำกว่า ROP)", "🟢 ปกติ")) -> 🔴 วิกฤต! (ของหมด) | X81: 6 | Y81: Maintenance Team | Z81: 0
A82: 81 | B82: Auto slit | C82: Auto-Cut | D82: Slit-01 | G82: Electrical System | H82: PT-81 | I82: Relay | J82: B | M82: PCS | N82: 0 | O82: AR-81 | P82: 1 | Q82: 1 | R82: =ROUND(Q82*0.5,0) -> 1 | S82: =Q82+R82 -> 2 | T82: =SUMIF('Stock In Log'!C:C, H82, 'Stock In Log'!D:D) - SUMIF('Stock Out Log'!C:C, H82, 'Stock Out Log'!D:D) -> 0 | U82: =N82*T82 -> 0 | V82: =IF(T82<=0,"ควรสั่งซื้อ", IF(T82<=S82,"ควรสั่งซื้อ","ปกติ")) -> ควรสั่งซื้อ | W82: =IF(T82<=0, "🔴 วิกฤต! (ของหมด)", IF(T82<=S82, "🟡 ควรสั่งซื้อ (ต่ำกว่า ROP)", "🟢 ปกติ")) -> 🔴 วิกฤต! (ของหมด) | X82: 6 | Y82: Maintenance Team | Z82: 0
A83: 82 | B83: Auto Cab | C83: Auto-cab | D83: Cab-01 | G83: Electrical System | H83: PT-82 | I83: Relay | J83: A | M83: PCS | N83: 0 | O83: AR-82 | P83: 1 | Q83: 1 | R83: =ROUND(Q83*0.5,0) -> 1 | S83: =Q83+R83 -> 2 | T83: =SUMIF('Stock In Log'!C:C, H83, 'Stock In Log'!D:D) - SUMIF('Stock Out Log'!C:C, H83, 'Stock Out Log'!D:D) -> 0 | U83: =N83*T83 -> 0 | V83: =IF(T83<=0,"ควรสั่งซื้อ", IF(T83<=S83,"ควรสั่งซื้อ","ปกติ")) -> ควรสั่งซื้อ | W83: =IF(T83<=0, "🔴 วิกฤต! (ของหมด)", IF(T83<=S83, "🟡 ควรสั่งซื้อ (ต่ำกว่า ROP)", "🟢 ปกติ")) -> 🔴 วิกฤต! (ของหมด) | X83: 6 | Y83: Maintenance Team | Z83: 0
A84: 83 | B84: Auto Cab | C84: Auto-cab | D84: Cab-01 | G84: Electrical System | H84: PT-83 | I84: PLC Controller | J84: A | M84: PCS | N84: 0 | O84: AR-83 | P84: 1 | Q84: 1 | R84: =ROUND(Q84*0.5,0) -> 1 | S84: =Q84+R84 -> 2 | T84: =SUMIF('Stock In Log'!C:C, H84, 'Stock In Log'!D:D) - SUMIF('Stock Out Log'!C:C, H84, 'Stock Out Log'!D:D) -> 0 | U84: =N84*T84 -> 0 | V84: =IF(T84<=0,"ควรสั่งซื้อ", IF(T84<=S84,"ควรสั่งซื้อ","ปกติ")) -> ควรสั่งซื้อ | W84: =IF(T84<=0, "🔴 วิกฤต! (ของหมด)", IF(T84<=S84, "🟡 ควรสั่งซื้อ (ต่ำกว่า ROP)", "🟢 ปกติ")) -> 🔴 วิกฤต! (ของหมด) | X84: 6 | Y84: Maintenance Team | Z84: 0
A85: 84 | B85: Boiler | C85: Boiler | D85: BO-01 | G85: Electrical System | H85: PT-84 | I85: PLC Controller | J85: A | M85: PCS | N85: 0 | O85: AR-84 | P85: 1 | Q85: 1 | R85: =ROUND(Q85*0.5,0) -> 1 | S85: =Q85+R85 -> 2 | T85: =SUMIF('Stock In Log'!C:C, H85, 'Stock In Log'!D:D) - SUMIF('Stock Out Log'!C:C, H85, 'Stock Out Log'!D:D) -> 0 | U85: =N85*T85 -> 0 | V85: =IF(T85<=0,"ควรสั่งซื้อ", IF(T85<=S85,"ควรสั่งซื้อ","ปกติ")) -> ควรสั่งซื้อ | W85: =IF(T85<=0, "🔴 วิกฤต! (ของหมด)", IF(T85<=S85, "🟡 ควรสั่งซื้อ (ต่ำกว่า ROP)", "🟢 ปกติ")) -> 🔴 วิกฤต! (ของหมด) | X85: 9 | Y85: Maintenance Team | Z85: 0
A86: 85 | B86: N2O | C86: N2O | D86: N2-01 | G86: Electrical System | H86: PT-85 | I86: PLC Controller | J86: A | M86: PCS | N86: 0 | O86: AR-85 | P86: 1 | Q86: 1 | R86: =ROUND(Q86*0.5,0) -> 1 | S86: =Q86+R86 -> 2 | T86: =SUMIF('Stock In Log'!C:C, H86, 'Stock In Log'!D:D) - SUMIF('Stock Out Log'!C:C, H86, 'Stock Out Log'!D:D) -> 0 | U86: =N86*T86 -> 0 | V86: =IF(T86<=0,"ควรสั่งซื้อ", IF(T86<=S86,"ควรสั่งซื้อ","ปกติ")) -> ควรสั่งซื้อ | W86: =IF(T86<=0, "🔴 วิกฤต! (ของหมด)", IF(T86<=S86, "🟡 ควรสั่งซื้อ (ต่ำกว่า ROP)", "🟢 ปกติ")) -> 🔴 วิกฤต! (ของหมด) | X86: 9 | Y86: Maintenance Team | Z86: 0
... A89: 86 | B89: Air Compreesor | C89: AC | D89: AC-01 | G89: Electrical System | H89: PT-86 | I89: PLC Controller | J89: A | M89: PCS | N89: 0 | O89: AR-88 | P89: 1 | Q89: 1 | R89: =ROUND(Q89*0.5,0) -> 1 | S89: =Q89+R89 -> 2 | T89: =SUMIF('Stock In Log'!C:C, H89, 'Stock In Log'!D:D) - SUMIF('Stock Out Log'!C:C, H89, 'Stock Out Log'!D:D) -> 0 | U89: =N89*T89 -> 0 | V89: =IF(T89<=0,"ควรสั่งซื้อ", IF(T89<=S89,"ควรสั่งซื้อ","ปกติ")) -> ควรสั่งซื้อ | W89: =IF(T89<=0, "🔴 วิกฤต! (ของหมด)", IF(T89<=S89, "🟡 ควรสั่งซื้อ (ต่ำกว่า ROP)", "🟢 ปกติ")) -> 🔴 วิกฤต! (ของหมด) | X89: 9 | Y89: Maintenance Team | Z89: 0

Sheet Stock In Log
A1: Date | B1: Doc No. | C1: Part Code | D1: Qty In | E1: Receiver
A2: 2026-05-01 | B2: INIT-001 | C2: PT-01 | D2: 2 | E2: Store_Admin
A3: 2026-05-01 | B3: INIT-001 | C3: PT-02 | D3: 2 | E3: Store_Admin
A4: 2026-05-01 | B4: INIT-001 | C4: PT-03 | D4: 2 | E4: Store_Admin
A5: 2026-05-01 | B5: INIT-001 | C5: PT-04 | D5: 2 | E5: Store_Admin
A6: 2026-05-01 | B6: INIT-001 | C6: PT-05 | D6: 3 | E6: Store_Admin
A7: 2026-05-01 | B7: INIT-001 | C7: PT-06 | D7: 3 | E7: Store_Admin
A8: 2026-05-01 | B8: INIT-001 | C8: PT-07 | D8: 2 | E8: Store_Admin
A9: 2026-05-01 | B9: INIT-001 | C9: PT-08 | D9: 2 | E9: Store_Admin
A10: 2026-05-01 | B10: INIT-001 | C10: PT-09 | D10: 2 | E10: Store_Admin
A11: 2026-05-01 | B11: INIT-001 | C11: PT-10 | D11: 2 | E11: Store_Admin
A12: 2026-05-01 | B12: INIT-001 | C12: PT-11 | D12: 2 | E12: Store_Admin
A13: 2026-05-01 | B13: INIT-001 | C13: PT-12 | D13: 2 | E13: Store_Admin
... A74: 2026-05-01 | B74: INIT-001 | C74: PT-73 | D74: 2 | E74: Store_Admin

Sheet Stock Out Log
A1: Date | B1: Doc No. | C1: Part Code | D1: Qty Out | E1: Requester | F1: Machine Code | G1: Reason
A2: 2026-05-12 | B2: REQ-2026001 | C2: PT-01 | D2: 2 | E2: ช่างสมชาย | F2: C16 | G2: อะไหล่เสื่อมสภาพตามรอบการใช้งาน (PM)
A3: 2026-05-12 | B3: REQ-2026001 | C3: PT-02 | D3: 2 | E3: ช่างสมชาย | F3: B17 | G3: อะไหล่เสื่อมสภาพตามรอบการใช้งาน (PM)
A4: 2026-05-12 | B4: REQ-2026001 | C4: PT-03 | D4: 2 | E4: ช่างสมชาย | F4: B17 | G4: อะไหล่เสื่อมสภาพตามรอบการใช้งาน (PM)
A5: 2026-05-12 | B5: REQ-2026001 | C5: PT-04 | D5: 2 | E5: ช่างสมชาย | F5: - | G5: อะไหล่เสื่อมสภาพตามรอบการใช้งาน (PM)
A6: 2026-05-12 | B6: REQ-2026001 | C6: PT-05 | D6: 2 | E6: ช่างสมชาย | F6: - | G6: อะไหล่เสื่อมสภาพตามรอบการใช้งาน (PM)
A7: 2026-05-12 | B7: REQ-2026001 | C7: PT-06 | D7: 2 | E7: ช่างสมชาย | F7: - | G7: อะไหล่เสื่อมสภาพตามรอบการใช้งาน (PM)
A8: 2026-05-12 | B8: REQ-2026001 | C8: PT-07 | D8: 2 | E8: ช่างสมชาย | F8: - | G8: อะไหล่เสื่อมสภาพตามรอบการใช้งาน (PM)
A9: 2026-05-12 | B9: REQ-2026001 | C9: PT-08 | D9: 2 | E9: ช่างสมชาย | F9: - | G9: อะไหล่เสื่อมสภาพตามรอบการใช้งาน (PM)
A10: 2026-05-12 | B10: REQ-2026001 | C10: PT-09 | D10: 2 | E10: ช่างสมชาย | F10: - | G10: อะไหล่เสื่อมสภาพตามรอบการใช้งาน (PM)
A11: 2026-05-12 | B11: REQ-2026001 | C11: PT-10 | D11: 2 | E11: ช่างสมชาย | F11: - | G11: อะไหล่เสื่อมสภาพตามรอบการใช้งาน (PM)
A12: 2026-05-12 | B12: REQ-2026001 | C12: PT-11 | D12: 2 | E12: ช่างสมชาย | F12: - | G12: อะไหล่เสื่อมสภาพตามรอบการใช้งาน (PM)
A13: 2026-05-12 | B13: REQ-2026001 | C13: PT-12 | D13: 2 | E13: ช่างสมชาย | F13: - | G13: อะไหล่เสื่อมสภาพตามรอบการใช้งาน (PM)
... A74: 2026-05-12 | B74: REQ-2026001 | C74: PT-73 | D74: 2 | E74: ช่างสมชาย | F74: EX-01 | G74: อะไหล่เสื่อมสภาพตามรอบการใช้งาน (PM)

Sheet Improvement_Recom
A1: Machine Spare Part Control - Improvement Recommendation
A3: Area | B3: Current Situation | C3: Gap / Weakness | D3: Recommended Improvement | E3: Benefit | F3: Priority | G3: Owner | H3: Timeline
A4: Master Data | B4: ยังไม่มี Machine Criticality Score | C4: วัดความเสี่ยงเครื่องจักรไม่แม่น | D4: เพิ่มคะแนน Criticality ตาม Production Impact / Safety / Quality | E4: จัดลำดับการถือ Stock ได้แม่นขึ้น | F4: High | G4: Maintenance | H4: 1 Month
A5: Inventory Control | B5: มี Min-Max แต่ยังไม่มี Safety Stock | C5: เสี่ยง Stock Out | D5: เพิ่มสูตร Safety Stock และ ROP | E5: ลด Emergency Purchase | F5: High | G5: Store + Purchasing | H5: 2 Weeks
A6: Dashboard | B6: มี KPI พื้นฐาน | C6: ยังไม่มี Pareto และ Trend | D6: เพิ่ม Pareto Top Failure และ Monthly Trend | E6: ผู้บริหารเห็นปัญหาหลักทันที | F6: High | G6: Engineering | H6: 1 Month
A7: Breakdown Analysis | B7: มี Breakdown History | C7: ยังไม่วิเคราะห์ MTBF/MTTR | D7: เพิ่ม MTBF และ MTTR Dashboard | E7: วิเคราะห์ Reliability ได้ | F7: Medium | G7: Maintenance | H7: 1 Month
A8: Dead Stock | B8: มี Aging | C8: ยังไม่มี Cost Impact | D8: เพิ่ม Dead Stock Cost Summary | E8: ลดทุนจม | F8: High | G8: Store | H8: 2 Weeks
A9: Supplier Control | B9: มี Supplier Name | C9: ยังไม่มี Supplier KPI | D9: เพิ่ม On-Time Delivery และ Quality KPI | E9: ประเมิน Vendor ได้ | F9: Medium | G9: Purchasing | H9: 1 Month
A10: PM Planning | B10: มี PM Schedule | C10: ยังไม่เชื่อม Spare Usage | D10: เชื่อม PM กับ Spare Consumption | E10: Forecast อะไหล่ได้แม่นขึ้น | F10: High | G10: Maintenance | H10: 1 Month
A11: Presentation | B11: ยังไม่มี Executive Summary | C11: ผู้บริหารดูข้อมูลยาก | D11: เพิ่มหน้า Summary Dashboard 1 Page | E11: ใช้ Present ผู้บริหารได้ทันที | F11: Critical | G11: Engineering | H11: 1 Week
B22: Machine Criticality Score
B23: คะแนน 9 (วิกฤตสูงสุด)
B24: คะแนน 6 (ความเสี่ยงปานกลาง-สูง)
B25: คะแนน 3 (ความเสี่ยงต่ำ)

Sheet Presentation_Guide
A1: Presentation Structure Recommendation
A3: Slide 1 | B3: Current Spare Part Situation | C3: แสดงปัญหา Overstock / Breakdown / Emergency Purchase
A4: Slide 2 | B4: Criticality Matrix | C4: แสดง Machine Rank vs Part Rank
A5: Slide 3 | B5: Current Inventory KPI | C5: Inventory Accuracy / Dead Stock / Reorder
A6: Slide 4 | B6: Top Breakdown Analysis | C6: Pareto Top Failure Part
A7: Slide 5 | B7: Dead Stock Cost | C7: มูลค่าของค้างคลัง
A8: Slide 6 | B8: Improvement Plan | C8: Action Plan + Timeline
A9: Slide 7 | B9: Expected Benefit | C9: ลด Downtime / ลด Stock / ลด Cost

Sheet Executive_Dashboard
A1: Machine Spare Part Executive Dashboard
A3: KPI | B3: Target | C3: Actual | D3: Status
A4: Inventory Accuracy % | B4: 98 | C4: 96 | D4: Below Target
A5: Critical Part Availability % | B5: 100 | C5: 95 | D5: Critical
A6: Dead Stock Value | B6: 50000 | C6: 145000 | D6: High
A7: Emergency Purchase % | B7: 5 | C7: 8 | D7: High
A12: MC Group Summary + Risk Zone
A14: MC Group | B14: Machine Count | C14: Spare Part Qty | D14: Inventory Value (THB) | E14: Critical Parts | F14: Reorder Items | G14: Risk Zone
A15: Compression | B15: 12 | C15: 320 | D15: 1250000 | E15: 48 | F15: 12 | G15: HIGH RISK
A16: Injection | B16: 8 | C16: 240 | D16: 980000 | E16: 35 | F16: 8 | G16: HIGH RISK
A17: Vacuum | B17: 5 | C17: 120 | D17: 450000 | E17: 15 | F17: 3 | G17: MEDIUM RISK
A18: CNC | B18: 4 | C18: 90 | D18: 780000 | E18: 18 | F18: 5 | G18: MEDIUM RISK
A19: Utility | B19: 10 | C19: 150 | D19: 220000 | E19: 5 | F19: 1 | G19: LOW RISK
A25: Risk Zone | B25: Count
A26: HIGH | B26: 2
A27: MEDIUM | B27: 2
A28: LOW | B28: 1
A40: Executive Key Focus
A42: 1. Compression และ Injection มีความเสี่ยงสูงสุด
A43: 2. Critical Part ต้อง Maintain Safety Stock
A44: 3. Dead Stock สูงเกิน Target
A45: 4. ควรลด Emergency Purchase และติดตาม Supplier Lead Time
